Workbook

Sheet SUGESTAO_LOJA
A1: PREÇO DE VENDA - CHIQUINHO SORVETES | S1: MÉDIA % INSUMO | V1: MÉDIA % LUCRO REAL | Y1: MÉDIA % CUSTO REAL
S2: =AVERAGE(Q5:Q384) -> 0.28466386 | V2: =AVERAGE(J5:J384) -> 0.20312345 | Y2: =SUM(Tabela25[Total Custo])/SUM(Tabela25[Total Venda]) -> #DIV/0!
A4: CÓDIGO | B4: GRUPO | C4: NOME GRUPO | D4: DESCRIÇÃO DO ITEM | E4: VENDA MIN | F4: VENDA MAX | G4: SUGESTÃO | H4: DIFERENÇA | I4: PREÇO PRATICADO | J4: LUCRO REAL % | K4: LUCRO REAL R$ | L4: QUANT. VENDA | M4: % CUSTO REAL | N4: CUSTO | O4: Total Venda | P4: Total Custo | Q4: % INSUMOS
A5: 101400048 | B5: 1014 | C5: Acai | D5: Açai Monte o Seu 300ml | E5: 18 | F5: 20 | G5: =VLOOKUP(Tabela25[[#This Row],[CÓDIGO]],'[1]Estrutura Loja'!$B$3:$M$2941,5,0) -> 23.968455 | H5: =E5-G5 -> -5.9684548 | I5: 18 | J5: =(Tabela25[[#This Row],[PREÇO PRATICADO]]-((Tabela25[[#This Row],[PREÇO PRATICADO]])*([1]Informações!$H$6+[1]Informações!$H$15+[1]Informações!$H$19+[1]Informações!$H$20))-Tabela25[[#This Row],[CUSTO]])/Tabela25[[#This Row],[PREÇO PRATICADO]] -> 0.10782053 | K5: =Tabela25[[#This Row],[PREÇO PRATICADO]]*Tabela25[[#This Row],[LUCRO REAL %]] -> 1.9407696 | L5: 0 | M5: =IF(Tabela25[[#This Row],[QUANT. VENDA]]=0,0,((Tabela25[[#This Row],[CUSTO]]*Tabela25[[#This Row],[QUANT. VENDA]])/(Tabela25[[#This Row],[QUANT. VENDA]]*Tabela25[[#This Row],[PREÇO PRATICADO]]))) -> 0 | N5: =VLOOKUP(Tabela25[[#This Row],[CÓDIGO]],'[1]Estrutura Loja'!$B$3:$E$1825,4,0) -> 6.6632304 | O5: =Tabela25[[#This Row],[QUANT. VENDA]]*Tabela25[[#This Row],[PREÇO PRATICADO]] -> 0 | P5: =Tabela25[[#This Row],[QUANT. VENDA]]*Tabela25[[#This Row],[CUSTO]] -> 0 | Q5: =Tabela25[[#This Row],[CUSTO]]/Tabela25[[#This Row],[PREÇO PRATICADO]] -> 0.37017947
A6: 101400049 | B6: 1014 | C6: Acai | D6: Açai Monte o Seu 400ml | E6: 23 | F6: 25 | G6: =VLOOKUP(Tabela25[[#This Row],[CÓDIGO]],'[1]Estrutura Loja'!$B$3:$M$2941,5,0) -> 31.660926 | H6: =E6-G6 -> -8.6609262 | I6: 23 | J6: =(Tabela25[[#This Row],[PREÇO PRATICADO]]-((Tabela25[[#This Row],[PREÇO PRATICADO]])*([1]Informações!$H$6+[1]Informações!$H$15+[1]Informações!$H$19+[1]Informações!$H$20))-Tabela25[[#This Row],[CUSTO]])/Tabela25[[#This Row],[PREÇO PRATICADO]] -> 0.095315762 | K6: =Tabela25[[#This Row],[PREÇO PRATICADO]]*Tabela25[[#This Row],[LUCRO REAL %]] -> 2.1922625 | M6: =IF(Tabela25[[#This Row],[QUANT. VENDA]]=0,0,((Tabela25[[#This Row],[CUSTO]]*Tabela25[[#This Row],[QUANT. VENDA]])/(Tabela25[[#This Row],[QUANT. VENDA]]*Tabela25[[#This Row],[PREÇO PRATICADO]]))) -> 0 | N6: =VLOOKUP(Tabela25[[#This Row],[CÓDIGO]],'[1]Estrutura Loja'!$B$3:$E$1825,4,0) -> 8.8017375 | O6: =Tabela25[[#This Row],[QUANT. VENDA]]*Tabela25[[#This Row],[PREÇO PRATICADO]] -> 0 | P6: =Tabela25[[#This Row],[QUANT. VENDA]]*Tabela25[[#This Row],[CUSTO]] -> 0 | Q6: =Tabela25[[#This Row],[CUSTO]]/Tabela25[[#This Row],[PREÇO PRATICADO]] -> 0.38268424 | S6: *Média s/ Adicional, Açaí, Pote e Ed. Limitada
A7: 101400050 | B7: 1014 | C7: Acai | D7: Açai Monte o Seu 500ml | E7: 27 | F7: 29 | G7: =VLOOKUP(Tabela25[[#This Row],[CÓDIGO]],'[1]Estrutura Loja'!$B$3:$M$2941,5,0) -> 39.223772 | H7: =E7-G7 -> -12.223772 | I7: 27 | J7: =(Tabela25[[#This Row],[PREÇO PRATICADO]]-((Tabela25[[#This Row],[PREÇO PRATICADO]])*([1]Informações!$H$6+[1]Informações!$H$15+[1]Informações!$H$19+[1]Informações!$H$20))-Tabela25[[#This Row],[CUSTO]])/Tabela25[[#This Row],[PREÇO PRATICADO]] -> 0.074140425 | K7: =Tabela25[[#This Row],[PREÇO PRATICADO]]*Tabela25[[#This Row],[LUCRO REAL %]] -> 2.0017915 | M7: =IF(Tabela25[[#This Row],[QUANT. VENDA]]=0,0,((Tabela25[[#This Row],[CUSTO]]*Tabela25[[#This Row],[QUANT. VENDA]])/(Tabela25[[#This Row],[QUANT. VENDA]]*Tabela25[[#This Row],[PREÇO PRATICADO]]))) -> 0 | N7: =VLOOKUP(Tabela25[[#This Row],[CÓDIGO]],'[1]Estrutura Loja'!$B$3:$E$1825,4,0) -> 10.904209 | O7: =Tabela25[[#This Row],[QUANT. VENDA]]*Tabela25[[#This Row],[PREÇO PRATICADO]] -> 0 | P7: =Tabela25[[#This Row],[QUANT. VENDA]]*Tabela25[[#This Row],[CUSTO]] -> 0 | Q7: =Tabela25[[#This Row],[CUSTO]]/Tabela25[[#This Row],[PREÇO PRATICADO]] -> 0.40385958
A8: 140000001 | B8: 1014 | C8: Acai | D8: Ad Aç Amendoim triturado | E8: 2.5 | F8: 3 | G8: =VLOOKUP(Tabela25[[#This Row],[CÓDIGO]],'[1]Estrutura Loja'!$B$3:$M$2941,5,0) -> 2.553741 | H8: =E8-G8 -> -0.053741007 | I8: 2.5 | J8: =(Tabela25[[#This Row],[PREÇO PRATICADO]]-((Tabela25[[#This Row],[PREÇO PRATICADO]])*([1]Informações!$H$6+[1]Informações!$H$15+[1]Informações!$H$19+[1]Informações!$H$20))-Tabela25[[#This Row],[CUSTO]])/Tabela25[[#This Row],[PREÇO PRATICADO]] -> 0.194024 | K8: =Tabela25[[#This Row],[PREÇO PRATICADO]]*Tabela25[[#This Row],[LUCRO REAL %]] -> 0.48506 | M8: =IF(Tabela25[[#This Row],[QUANT. VENDA]]=0,0,((Tabela25[[#This Row],[CUSTO]]*Tabela25[[#This Row],[QUANT. VENDA]])/(Tabela25[[#This Row],[QUANT. VENDA]]*Tabela25[[#This Row],[PREÇO PRATICADO]]))) -> 0 | N8: =VLOOKUP(Tabela25[[#This Row],[CÓDIGO]],'[1]Estrutura Loja'!$B$3:$E$1825,4,0) -> 0.70994 | O8: =Tabela25[[#This Row],[QUANT. VENDA]]*Tabela25[[#This Row],[PREÇO PRATICADO]] -> 0 | P8: =Tabela25[[#This Row],[QUANT. VENDA]]*Tabela25[[#This Row],[CUSTO]] -> 0 | Q8: =Tabela25[[#This Row],[CUSTO]]/Tabela25[[#This Row],[PREÇO PRATICADO]] -> 0.283976 | S8: MÉDIA % INSUMO | V8: MÉDIA % LUCRO REAL
A9: 140000002 | B9: 1014 | C9: Acai | D9: Ad Aç Banana | E9: 2 | F9: 2.5 | G9: =VLOOKUP(Tabela25[[#This Row],[CÓDIGO]],'[1]Estrutura Loja'!$B$3:$M$2941,5,0) -> 1.8658273 | H9: =E9-G9 -> 0.13417266 | I9: 2 | J9: =(Tabela25[[#This Row],[PREÇO PRATICADO]]-((Tabela25[[#This Row],[PREÇO PRATICADO]])*([1]Informações!$H$6+[1]Informações!$H$15+[1]Informações!$H$19+[1]Informações!$H$20))-Tabela25[[#This Row],[CUSTO]])/Tabela25[[#This Row],[PREÇO PRATICADO]] -> 0.21865 | K9: =Tabela25[[#This Row],[PREÇO PRATICADO]]*Tabela25[[#This Row],[LUCRO REAL %]] -> 0.4373 | M9: =IF(Tabela25[[#This Row],[QUANT. VENDA]]=0,0,((Tabela25[[#This Row],[CUSTO]]*Tabela25[[#This Row],[QUANT. VENDA]])/(Tabela25[[#This Row],[QUANT. VENDA]]*Tabela25[[#This Row],[PREÇO PRATICADO]]))) -> 0 | N9: =VLOOKUP(Tabela25[[#This Row],[CÓDIGO]],'[1]Estrutura Loja'!$B$3:$E$1825,4,0) -> 0.5187 | O9: =Tabela25[[#This Row],[QUANT. VENDA]]*Tabela25[[#This Row],[PREÇO PRATICADO]] -> 0 | P9: =Tabela25[[#This Row],[QUANT. VENDA]]*Tabela25[[#This Row],[CUSTO]] -> 0 | Q9: =Tabela25[[#This Row],[CUSTO]]/Tabela25[[#This Row],[PREÇO PRATICADO]] -> 0.25935 | S9: 0.28 | V9: 0.21
A10: 140000003 | B10: 1014 | C10: Acai | D10: Ad Aç Morango | E10: 7.5 | F10: 8.5 | G10: =VLOOKUP(Tabela25[[#This Row],[CÓDIGO]],'[1]Estrutura Loja'!$B$3:$M$2941,5,0) -> 7.5539568 | H10: =E10-G10 -> -0.053956835 | I10: 7.5 | J10: =(Tabela25[[#This Row],[PREÇO PRATICADO]]-((Tabela25[[#This Row],[PREÇO PRATICADO]])*([1]Informações!$H$6+[1]Informações!$H$15+[1]Informações!$H$19+[1]Informações!$H$20))-Tabela25[[#This Row],[CUSTO]])/Tabela25[[#This Row],[PREÇO PRATICADO]] -> 0.198 | K10: =Tabela25[[#This Row],[PREÇO PRATICADO]]*Tabela25[[#This Row],[LUCRO REAL %]] -> 1.485 | M10: =IF(Tabela25[[#This Row],[QUANT. VENDA]]=0,0,((Tabela25[[#This Row],[CUSTO]]*Tabela25[[#This Row],[QUANT. VENDA]])/(Tabela25[[#This Row],[QUANT. VENDA]]*Tabela25[[#This Row],[PREÇO PRATICADO]]))) -> 0 | N10: =VLOOKUP(Tabela25[[#This Row],[CÓDIGO]],'[1]Estrutura Loja'!$B$3:$E$1825,4,0) -> 2.1 | O10: =Tabela25[[#This Row],[QUANT. VENDA]]*Tabela25[[#This Row],[PREÇO PRATICADO]] -> 0 | P10: =Tabela25[[#This Row],[QUANT. VENDA]]*Tabela25[[#This Row],[CUSTO]] -> 0 | Q10: =Tabela25[[#This Row],[CUSTO]]/Tabela25[[#This Row],[PREÇO PRATICADO]] -> 0.28
A11: 140000004 | B11: 1014 | C11: Acai | D11: Ad Aç Mini Disqueti | E11: 9.5 | F11: 10.5 | G11: =VLOOKUP(Tabela25[[#This Row],[CÓDIGO]],'[1]Estrutura Loja'!$B$3:$M$2941,5,0) -> 11.854676 | H11: =E11-G11 -> -2.3546763 | I11: 9.5 | J11: =(Tabela25[[#This Row],[PREÇO PRATICADO]]-((Tabela25[[#This Row],[PREÇO PRATICADO]])*([1]Informações!$H$6+[1]Informações!$H$15+[1]Informações!$H$19+[1]Informações!$H$20))-Tabela25[[#This Row],[CUSTO]])/Tabela25[[#This Row],[PREÇO PRATICADO]] -> 0.13109474 | K11: =Tabela25[[#This Row],[PREÇO PRATICADO]]*Tabela25[[#This Row],[LUCRO REAL %]] -> 1.2454 | M11: =IF(Tabela25[[#This Row],[QUANT. VENDA]]=0,0,((Tabela25[[#This Row],[CUSTO]]*Tabela25[[#This Row],[QUANT. VENDA]])/(Tabela25[[#This Row],[QUANT. VENDA]]*Tabela25[[#This Row],[PREÇO PRATICADO]]))) -> 0 | N11: =VLOOKUP(Tabela25[[#This Row],[CÓDIGO]],'[1]Estrutura Loja'!$B$3:$E$1825,4,0) -> 3.2956 | O11: =Tabela25[[#This Row],[QUANT. VENDA]]*Tabela25[[#This Row],[PREÇO PRATICADO]] -> 0 | P11: =Tabela25[[#This Row],[QUANT. VENDA]]*Tabela25[[#This Row],[CUSTO]] -> 0 | Q11: =Tabela25[[#This Row],[CUSTO]]/Tabela25[[#This Row],[PREÇO PRATICADO]] -> 0.34690526
A12: 140000005 | B12: 1014 | C12: Acai | D12: Ad Aç Leite Ninho | E12: 4.5 | F12: 4.5 | G12: =VLOOKUP(Tabela25[[#This Row],[CÓDIGO]],'[1]Estrutura Loja'!$B$3:$M$2941,5,0) -> 4.4527578 | H12: =E12-G12 -> 0.047242206 | I12: 4.5 | J12: =(Tabela25[[#This Row],[PREÇO PRATICADO]]-((Tabela25[[#This Row],[PREÇO PRATICADO]])*([1]Informações!$H$6+[1]Informações!$H$15+[1]Informações!$H$19+[1]Informações!$H$20))-Tabela25[[#This Row],[CUSTO]])/Tabela25[[#This Row],[PREÇO PRATICADO]] -> 0.20291852 | K12: =Tabela25[[#This Row],[PREÇO PRATICADO]]*Tabela25[[#This Row],[LUCRO REAL %]] -> 0.91313333 | M12: =IF(Tabela25[[#This Row],[QUANT. VENDA]]=0,0,((Tabela25[[#This Row],[CUSTO]]*Tabela25[[#This Row],[QUANT. VENDA]])/(Tabela25[[#This Row],[QUANT. VENDA]]*Tabela25[[#This Row],[PREÇO PRATICADO]]))) -> 0 | N12: =VLOOKUP(Tabela25[[#This Row],[CÓDIGO]],'[1]Estrutura Loja'!$B$3:$E$1825,4,0) -> 1.2378667 | O12: =Tabela25[[#This Row],[QUANT. VENDA]]*Tabela25[[#This Row],[PREÇO PRATICADO]] -> 0 | P12: =Tabela25[[#This Row],[QUANT. VENDA]]*Tabela25[[#This Row],[CUSTO]] -> 0 | Q12: =Tabela25[[#This Row],[CUSTO]]/Tabela25[[#This Row],[PREÇO PRATICADO]] -> 0.27508148
A13: 140000006 | B13: 1014 | C13: Acai | D13: Ad Aç Chocolate granulado | E13: 2.5 | F13: 3.5 | G13: =VLOOKUP(Tabela25[[#This Row],[CÓDIGO]],'[1]Estrutura Loja'!$B$3:$M$2941,5,0) -> 2.4446186 | H13: =E13-G13 -> 0.055381437 | I13: 2.5 | J13: =(Tabela25[[#This Row],[PREÇO PRATICADO]]-((Tabela25[[#This Row],[PREÇO PRATICADO]])*([1]Informações!$H$6+[1]Informações!$H$15+[1]Informações!$H$19+[1]Informações!$H$20))-Tabela25[[#This Row],[CUSTO]])/Tabela25[[#This Row],[PREÇO PRATICADO]] -> 0.20615842 | K13: =Tabela25[[#This Row],[PREÇO PRATICADO]]*Tabela25[[#This Row],[LUCRO REAL %]] -> 0.51539604 | M13: =IF(Tabela25[[#This Row],[QUANT. VENDA]]=0,0,((Tabela25[[#This Row],[CUSTO]]*Tabela25[[#This Row],[QUANT. VENDA]])/(Tabela25[[#This Row],[QUANT. VENDA]]*Tabela25[[#This Row],[PREÇO PRATICADO]]))) -> 0 | N13: =VLOOKUP(Tabela25[[#This Row],[CÓDIGO]],'[1]Estrutura Loja'!$B$3:$E$1825,4,0) -> 0.67960396 | O13: =Tabela25[[#This Row],[QUANT. VENDA]]*Tabela25[[#This Row],[PREÇO PRATICADO]] -> 0 | P13: =Tabela25[[#This Row],[QUANT. VENDA]]*Tabela25[[#This Row],[CUSTO]] -> 0 | Q13: =Tabela25[[#This Row],[CUSTO]]/Tabela25[[#This Row],[PREÇO PRATICADO]] -> 0.27184158
A14: 140000007 | B14: 1014 | C14: Acai | D14: Ad Aç Ovomaltine | E14: 3 | F14: 4 | G14: =VLOOKUP(Tabela25[[#This Row],[CÓDIGO]],'[1]Estrutura Loja'!$B$3:$M$2941,5,0) -> 3.3444221 | H14: =E14-G14 -> -0.34442206 | I14: 3 | J14: =(Tabela25[[#This Row],[PREÇO PRATICADO]]-((Tabela25[[#This Row],[PREÇO PRATICADO]])*([1]Informações!$H$6+[1]Informações!$H$15+[1]Informações!$H$19+[1]Informações!$H$20))-Tabela25[[#This Row],[CUSTO]])/Tabela25[[#This Row],[PREÇO PRATICADO]] -> 0.16808356 | K14: =Tabela25[[#This Row],[PREÇO PRATICADO]]*Tabela25[[#This Row],[LUCRO REAL %]] -> 0.50425067 | M14: =IF(Tabela25[[#This Row],[QUANT. VENDA]]=0,0,((Tabela25[[#This Row],[CUSTO]]*Tabela25[[#This Row],[QUANT. VENDA]])/(Tabela25[[#This Row],[QUANT. VENDA]]*Tabela25[[#This Row],[PREÇO PRATICADO]]))) -> 0 | N14: =VLOOKUP(Tabela25[[#This Row],[CÓDIGO]],'[1]Estrutura Loja'!$B$3:$E$1825,4,0) -> 0.92974933 | O14: =Tabela25[[#This Row],[QUANT. VENDA]]*Tabela25[[#This Row],[PREÇO PRATICADO]] -> 0 | P14: =Tabela25[[#This Row],[QUANT. VENDA]]*Tabela25[[#This Row],[CUSTO]] -> 0 | Q14: =Tabela25[[#This Row],[CUSTO]]/Tabela25[[#This Row],[PREÇO PRATICADO]] -> 0.30991644
A15: 140000008 | B15: 1014 | C15: =VLOOKUP(Tabela25[[#This Row],[GRUPO]],[1]Produto!H14:I363,2,0) -> Acai | D15: Ad Aç Leite Condensado Moça | E15: 5 | F15: 6 | G15: =VLOOKUP(Tabela25[[#This Row],[CÓDIGO]],'[1]Estrutura Loja'!$B$3:$M$2941,5,0) -> 5.0537292 | H15: =E15-G15 -> -0.053729169 | I15: 5 | J15: =(Tabela25[[#This Row],[PREÇO PRATICADO]]-((Tabela25[[#This Row],[PREÇO PRATICADO]])*([1]Informações!$H$6+[1]Informações!$H$15+[1]Informações!$H$19+[1]Informações!$H$20))-Tabela25[[#This Row],[CUSTO]])/Tabela25[[#This Row],[PREÇO PRATICADO]] -> 0.19701266 | K15: =Tabela25[[#This Row],[PREÇO PRATICADO]]*Tabela25[[#This Row],[LUCRO REAL %]] -> 0.98506329 | M15: =IF(Tabela25[[#This Row],[QUANT. VENDA]]=0,0,((Tabela25[[#This Row],[CUSTO]]*Tabela25[[#This Row],[QUANT. VENDA]])/(Tabela25[[#This Row],[QUANT. VENDA]]*Tabela25[[#This Row],[PREÇO PRATICADO]]))) -> 0 | N15: =VLOOKUP(Tabela25[[#This Row],[CÓDIGO]],'[1]Estrutura Loja'!$B$3:$E$1825,4,0) -> 1.4049367 | O15: =Tabela25[[#This Row],[QUANT. VENDA]]*Tabela25[[#This Row],[PREÇO PRATICADO]] -> 0 | P15: =Tabela25[[#This Row],[QUANT. VENDA]]*Tabela25[[#This Row],[CUSTO]] -> 0 | Q15: =Tabela25[[#This Row],[CUSTO]]/Tabela25[[#This Row],[PREÇO PRATICADO]] -> 0.28098734
A16: 140000009 | B16: 1014 | C16: Acai | D16: Ad Aç Ganache chiquinho | E16: 7.5 | F16: 8.5 | G16: =VLOOKUP(Tabela25[[#This Row],[CÓDIGO]],'[1]Estrutura Loja'!$B$3:$M$2941,5,0) -> 8.9503597 | H16: =E16-G16 -> -1.4503597 | I16: 7.5 | J16: =(Tabela25[[#This Row],[PREÇO PRATICADO]]-((Tabela25[[#This Row],[PREÇO PRATICADO]])*([1]Informações!$H$6+[1]Informações!$H$15+[1]Informações!$H$19+[1]Informações!$H$20))-Tabela25[[#This Row],[CUSTO]])/Tabela25[[#This Row],[PREÇO PRATICADO]] -> 0.14624 | K16: =Tabela25[[#This Row],[PREÇO PRATICADO]]*Tabela25[[#This Row],[LUCRO REAL %]] -> 1.0968 | M16: =IF(Tabela25[[#This Row],[QUANT. VENDA]]=0,0,((Tabela25[[#This Row],[CUSTO]]*Tabela25[[#This Row],[QUANT. VENDA]])/(Tabela25[[#This Row],[QUANT. VENDA]]*Tabela25[[#This Row],[PREÇO PRATICADO]]))) -> 0 | N16: =VLOOKUP(Tabela25[[#This Row],[CÓDIGO]],'[1]Estrutura Loja'!$B$3:$E$1825,4,0) -> 2.4882 | O16: =Tabela25[[#This Row],[QUANT. VENDA]]*Tabela25[[#This Row],[PREÇO PRATICADO]] -> 0 | P16: =Tabela25[[#This Row],[QUANT. VENDA]]*Tabela25[[#This Row],[CUSTO]] -> 0 | Q16: =Tabela25[[#This Row],[CUSTO]]/Tabela25[[#This Row],[PREÇO PRATICADO]] -> 0.33176
A17: 140000010 | B17: 1014 | C17: Acai | D17: Ad Aç Trufada Chiquinho | E17: 5 | F17: 6 | G17: =VLOOKUP(Tabela25[[#This Row],[CÓDIGO]],'[1]Estrutura Loja'!$B$3:$M$2941,5,0) -> 4.8098664 | H17: =E17-G17 -> 0.19013361 | I17: 5 | J17: =(Tabela25[[#This Row],[PREÇO PRATICADO]]-((Tabela25[[#This Row],[PREÇO PRATICADO]])*([1]Informações!$H$6+[1]Informações!$H$15+[1]Informações!$H$19+[1]Informações!$H$20))-Tabela25[[#This Row],[CUSTO]])/Tabela25[[#This Row],[PREÇO PRATICADO]] -> 0.21057143 | K17: =Tabela25[[#This Row],[PREÇO PRATICADO]]*Tabela25[[#This Row],[LUCRO REAL %]] -> 1.0528571 | M17: =IF(Tabela25[[#This Row],[QUANT. VENDA]]=0,0,((Tabela25[[#This Row],[CUSTO]]*Tabela25[[#This Row],[QUANT. VENDA]])/(Tabela25[[#This Row],[QUANT. VENDA]]*Tabela25[[#This Row],[PREÇO PRATICADO]]))) -> 0 | N17: =VLOOKUP(Tabela25[[#This Row],[CÓDIGO]],'[1]Estrutura Loja'!$B$3:$E$1825,4,0) -> 1.3371429 | O17: =Tabela25[[#This Row],[QUANT. VENDA]]*Tabela25[[#This Row],[PREÇO PRATICADO]] -> 0 | P17: =Tabela25[[#This Row],[QUANT. VENDA]]*Tabela25[[#This Row],[CUSTO]] -> 0 | Q17: =Tabela25[[#This Row],[CUSTO]]/Tabela25[[#This Row],[PREÇO PRATICADO]] -> 0.26742857
A18: 140000011 | B18: 1014 | C18: Acai | D18: Ad Aç Chantilly | E18: 2 | F18: 3 | G18: =VLOOKUP(Tabela25[[#This Row],[CÓDIGO]],'[1]Estrutura Loja'!$B$3:$M$2941,5,0) -> 2.2509521 | H18: =E18-G18 -> -0.25095213 | I18: 2 | J18: =(Tabela25[[#This Row],[PREÇO PRATICADO]]-((Tabela25[[#This Row],[PREÇO PRATICADO]])*([1]Informações!$H$6+[1]Informações!$H$15+[1]Informações!$H$19+[1]Informações!$H$20))-Tabela25[[#This Row],[CUSTO]])/Tabela25[[#This Row],[PREÇO PRATICADO]] -> 0.16511765 | K18: =Tabela25[[#This Row],[PREÇO PRATICADO]]*Tabela25[[#This Row],[LUCRO REAL %]] -> 0.33023531 | M18: =IF(Tabela25[[#This Row],[QUANT. VENDA]]=0,0,((Tabela25[[#This Row],[CUSTO]]*Tabela25[[#This Row],[QUANT. VENDA]])/(Tabela25[[#This Row],[QUANT. VENDA]]*Tabela25[[#This Row],[PREÇO PRATICADO]]))) -> 0 | N18: =VLOOKUP(Tabela25[[#This Row],[CÓDIGO]],'[1]Estrutura Loja'!$B$3:$E$1825,4,0) -> 0.62576469 | O18: =Tabela25[[#This Row],[QUANT. VENDA]]*Tabela25[[#This Row],[PREÇO PRATICADO]] -> 0 | P18: =Tabela25[[#This Row],[QUANT. VENDA]]*Tabela25[[#This Row],[CUSTO]] -> 0 | Q18: =Tabela25[[#This Row],[CUSTO]]/Tabela25[[#This Row],[PREÇO PRATICADO]] -> 0.31288235
A19: 140000012 | B19: 1014 | C19: Acai | D19: Ad Aç Doce de Leite | E19: 2.5 | F19: 3 | G19: =VLOOKUP(Tabela25[[#This Row],[CÓDIGO]],'[1]Estrutura Loja'!$B$3:$M$2941,5,0) -> 2.3535746 | H19: =E19-G19 -> 0.14642536 | I19: 2.5 | J19: =(Tabela25[[#This Row],[PREÇO PRATICADO]]-((Tabela25[[#This Row],[PREÇO PRATICADO]])*([1]Informações!$H$6+[1]Informações!$H$15+[1]Informações!$H$19+[1]Informações!$H$20))-Tabela25[[#This Row],[CUSTO]])/Tabela25[[#This Row],[PREÇO PRATICADO]] -> 0.2162825 | K19: =Tabela25[[#This Row],[PREÇO PRATICADO]]*Tabela25[[#This Row],[LUCRO REAL %]] -> 0.54070625 | M19: =IF(Tabela25[[#This Row],[QUANT. VENDA]]=0,0,((Tabela25[[#This Row],[CUSTO]]*Tabela25[[#This Row],[QUANT. VENDA]])/(Tabela25[[#This Row],[QUANT. VENDA]]*Tabela25[[#This Row],[PREÇO PRATICADO]]))) -> 0 | N19: =VLOOKUP(Tabela25[[#This Row],[CÓDIGO]],'[1]Estrutura Loja'!$B$3:$E$1825,4,0) -> 0.65429375 | O19: =Tabela25[[#This Row],[QUANT. VENDA]]*Tabela25[[#This Row],[PREÇO PRATICADO]] -> 0 | P19: =Tabela25[[#This Row],[QUANT. VENDA]]*Tabela25[[#This Row],[CUSTO]] -> 0 | Q19: =Tabela25[[#This Row],[CUSTO]]/Tabela25[[#This Row],[PREÇO PRATICADO]] -> 0.2617175
A20: 140000013 | B20: 1014 | C20: Acai | D20: Ad Aç Biscoito Negresco | E20: 5 | F20: 5 | G20: =VLOOKUP(Tabela25[[#This Row],[CÓDIGO]],'[1]Estrutura Loja'!$B$3:$M$2941,5,0) -> 4.0215827 | H20: =E20-G20 -> 0.97841727 | I20: 5 | J20: =(Tabela25[[#This Row],[PREÇO PRATICADO]]-((Tabela25[[#This Row],[PREÇO PRATICADO]])*([1]Informações!$H$6+[1]Informações!$H$15+[1]Informações!$H$19+[1]Informações!$H$20))-Tabela25[[#This Row],[CUSTO]])/Tabela25[[#This Row],[PREÇO PRATICADO]] -> 0.2544 | K20: =Tabela25[[#This Row],[PREÇO PRATICADO]]*Tabela25[[#This Row],[LUCRO REAL %]] -> 1.272 | M20: =IF(Tabela25[[#This Row],[QUANT. VENDA]]=0,0,((Tabela25[[#This Row],[CUSTO]]*Tabela25[[#This Row],[QUANT. VENDA]])/(Tabela25[[#This Row],[QUANT. VENDA]]*Tabela25[[#This Row],[PREÇO PRATICADO]]))) -> 0 | N20: =VLOOKUP(Tabela25[[#This Row],[CÓDIGO]],'[1]Estrutura Loja'!$B$3:$E$1825,4,0) -> 1.118 | O20: =Tabela25[[#This Row],[QUANT. VENDA]]*Tabela25[[#This Row],[PREÇO PRATICADO]] -> 0 | P20: =Tabela25[[#This Row],[QUANT. VENDA]]*Tabela25[[#This Row],[CUSTO]] -> 0 | Q20: =Tabela25[[#This Row],[CUSTO]]/Tabela25[[#This Row],[PREÇO PRATICADO]] -> 0.2236
A21: 140000014 | B21: 1014 | C21: Acai | D21: Ad Aç Marshmallow Torção fini | E21: 6 | F21: 6 | G21: =VLOOKUP(Tabela25[[#This Row],[CÓDIGO]],'[1]Estrutura Loja'!$B$3:$M$2941,5,0) -> 6.3777842 | H21: =E21-G21 -> -0.37778417 | I21: 6 | J21: =(Tabela25[[#This Row],[PREÇO PRATICADO]]-((Tabela25[[#This Row],[PREÇO PRATICADO]])*([1]Informações!$H$6+[1]Informações!$H$15+[1]Informações!$H$19+[1]Informações!$H$20))-Tabela25[[#This Row],[CUSTO]])/Tabela25[[#This Row],[PREÇO PRATICADO]] -> 0.182496 | K21: =Tabela25[[#This Row],[PREÇO PRATICADO]]*Tabela25[[#This Row],[LUCRO REAL %]] -> 1.094976 | M21: =IF(Tabela25[[#This Row],[QUANT. VENDA]]=0,0,((Tabela25[[#This Row],[CUSTO]]*Tabela25[[#This Row],[QUANT. VENDA]])/(Tabela25[[#This Row],[QUANT. VENDA]]*Tabela25[[#This Row],[PREÇO PRATICADO]]))) -> 0 | N21: =VLOOKUP(Tabela25[[#This Row],[CÓDIGO]],'[1]Estrutura Loja'!$B$3:$E$1825,4,0) -> 1.773024 | O21: =Tabela25[[#This Row],[QUANT. VENDA]]*Tabela25[[#This Row],[PREÇO PRATICADO]] -> 0 | P21: =Tabela25[[#This Row],[QUANT. VENDA]]*Tabela25[[#This Row],[CUSTO]] -> 0 | Q21: =Tabela25[[#This Row],[CUSTO]]/Tabela25[[#This Row],[PREÇO PRATICADO]] -> 0.295504
A22: 140000015 | B22: 1014 | C22: Acai | D22: Ad Aç Polpa Morango | E22: 5 | F22: 6 | G22: =VLOOKUP(Tabela25[[#This Row],[CÓDIGO]],'[1]Estrutura Loja'!$B$3:$M$2941,5,0) -> 5.5936612 | H22: =E22-G22 -> -0.59366117 | I22: 5 | J22: =(Tabela25[[#This Row],[PREÇO PRATICADO]]-((Tabela25[[#This Row],[PREÇO PRATICADO]])*([1]Informações!$H$6+[1]Informações!$H$15+[1]Informações!$H$19+[1]Informações!$H$20))-Tabela25[[#This Row],[CUSTO]])/Tabela25[[#This Row],[PREÇO PRATICADO]] -> 0.16699244 | K22: =Tabela25[[#This Row],[PREÇO PRATICADO]]*Tabela25[[#This Row],[LUCRO REAL %]] -> 0.8349622 | M22: =IF(Tabela25[[#This Row],[QUANT. VENDA]]=0,0,((Tabela25[[#This Row],[CUSTO]]*Tabela25[[#This Row],[QUANT. VENDA]])/(Tabela25[[#This Row],[QUANT. VENDA]]*Tabela25[[#This Row],[PREÇO PRATICADO]]))) -> 0 | N22: =VLOOKUP(Tabela25[[#This Row],[CÓDIGO]],'[1]Estrutura Loja'!$B$3:$E$1825,4,0) -> 1.5550378 | O22: =Tabela25[[#This Row],[QUANT. VENDA]]*Tabela25[[#This Row],[PREÇO PRATICADO]] -> 0 | P22: =Tabela25[[#This Row],[QUANT. VENDA]]*Tabela25[[#This Row],[CUSTO]] -> 0 | Q22: =Tabela25[[#This Row],[CUSTO]]/Tabela25[[#This Row],[PREÇO PRATICADO]] -> 0.31100756
A23: 140000016 | B23: 1014 | C23: Acai | D23: Ad Aç Polpa maracujá | E23: 6 | F23: 7 | G23: =VLOOKUP(Tabela25[[#This Row],[CÓDIGO]],'[1]Estrutura Loja'!$B$3:$M$2941,5,0) -> 6.1021758 | H23: =E23-G23 -> -0.10217582 | I23: 6 | J23: =(Tabela25[[#This Row],[PREÇO PRATICADO]]-((Tabela25[[#This Row],[PREÇO PRATICADO]])*([1]Informações!$H$6+[1]Informações!$H$15+[1]Informações!$H$19+[1]Informações!$H$20))-Tabela25[[#This Row],[CUSTO]])/Tabela25[[#This Row],[PREÇO PRATICADO]] -> 0.19526585 | K23: =Tabela25[[#This Row],[PREÇO PRATICADO]]*Tabela25[[#This Row],[LUCRO REAL %]] -> 1.1715951 | M23: =IF(Tabela25[[#This Row],[QUANT. VENDA]]=0,0,((Tabela25[[#This Row],[CUSTO]]*Tabela25[[#This Row],[QUANT. VENDA]])/(Tabela25[[#This Row],[QUANT. VENDA]]*Tabela25[[#This Row],[PREÇO PRATICADO]]))) -> 0 | N23: =VLOOKUP(Tabela25[[#This Row],[CÓDIGO]],'[1]Estrutura Loja'!$B$3:$E$1825,4,0) -> 1.6964049 | O23: =Tabela25[[#This Row],[QUANT. VENDA]]*Tabela25[[#This Row],[PREÇO PRATICADO]] -> 0 | P23: =Tabela25[[#This Row],[QUANT. VENDA]]*Tabela25[[#This Row],[CUSTO]] -> 0 | Q23: =Tabela25[[#This Row],[CUSTO]]/Tabela25[[#This Row],[PREÇO PRATICADO]] -> 0.28273415
A24: 140000017 | B24: 1014 | C24: Acai | D24: Ad Aç Polpa Frutas Vermelhas | E24: 6 | F24: 7 | G24: =VLOOKUP(Tabela25[[#This Row],[CÓDIGO]],'[1]Estrutura Loja'!$B$3:$M$2941,5,0) -> 7.0269345 | H24: =E24-G24 -> -1.0269345 | I24: 6 | J24: =(Tabela25[[#This Row],[PREÇO PRATICADO]]-((Tabela25[[#This Row],[PREÇO PRATICADO]])*([1]Informações!$H$6+[1]Informações!$H$15+[1]Informações!$H$19+[1]Informações!$H$20))-Tabela25[[#This Row],[CUSTO]])/Tabela25[[#This Row],[PREÇO PRATICADO]] -> 0.1524187 | K24: =Tabela25[[#This Row],[PREÇO PRATICADO]]*Tabela25[[#This Row],[LUCRO REAL %]] -> 0.9145122 | M24: =IF(Tabela25[[#This Row],[QUANT. VENDA]]=0,0,((Tabela25[[#This Row],[CUSTO]]*Tabela25[[#This Row],[QUANT. VENDA]])/(Tabela25[[#This Row],[QUANT. VENDA]]*Tabela25[[#This Row],[PREÇO PRATICADO]]))) -> 0 | N24: =VLOOKUP(Tabela25[[#This Row],[CÓDIGO]],'[1]Estrutura Loja'!$B$3:$E$1825,4,0) -> 1.9534878 | O24: =Tabela25[[#This Row],[QUANT. VENDA]]*Tabela25[[#This Row],[PREÇO PRATICADO]] -> 0 | P24: =Tabela25[[#This Row],[QUANT. VENDA]]*Tabela25[[#This Row],[CUSTO]] -> 0 | Q24: =Tabela25[[#This Row],[CUSTO]]/Tabela25[[#This Row],[PREÇO PRATICADO]] -> 0.3255813
A25: 140000018 | B25: 1014 | C25: Acai | D25: Ad Aç Creme Crocante Ovomaltine | E25: 7.5 | F25: 8.5 | G25: =VLOOKUP(Tabela25[[#This Row],[CÓDIGO]],'[1]Estrutura Loja'!$B$3:$M$2941,5,0) -> 7.5092806 | H25: =E25-G25 -> -0.0092805755 | I25: 7.5 | J25: =(Tabela25[[#This Row],[PREÇO PRATICADO]]-((Tabela25[[#This Row],[PREÇO PRATICADO]])*([1]Informações!$H$6+[1]Informações!$H$15+[1]Informações!$H$19+[1]Informações!$H$20))-Tabela25[[#This Row],[CUSTO]])/Tabela25[[#This Row],[PREÇO PRATICADO]] -> 0.199656 | K25: =Tabela25[[#This Row],[PREÇO PRATICADO]]*Tabela25[[#This Row],[LUCRO REAL %]] -> 1.49742 | M25: =IF(Tabela25[[#This Row],[QUANT. VENDA]]=0,0,((Tabela25[[#This Row],[CUSTO]]*Tabela25[[#This Row],[QUANT. VENDA]])/(Tabela25[[#This Row],[QUANT. VENDA]]*Tabela25[[#This Row],[PREÇO PRATICADO]]))) -> 0 | N25: =VLOOKUP(Tabela25[[#This Row],[CÓDIGO]],'[1]Estrutura Loja'!$B$3:$E$1825,4,0) -> 2.08758 | O25: =Tabela25[[#This Row],[QUANT. VENDA]]*Tabela25[[#This Row],[PREÇO PRATICADO]] -> 0 | P25: =Tabela25[[#This Row],[QUANT. VENDA]]*Tabela25[[#This Row],[CUSTO]] -> 0 | Q25: =Tabela25[[#This Row],[CUSTO]]/Tabela25[[#This Row],[PREÇO PRATICADO]] -> 0.278344
A26: 140000019 | B26: 1014 | C26: Acai | D26: Ad Aç Farofa Especial | E26: 4 | F26: 5 | G26: =VLOOKUP(Tabela25[[#This Row],[CÓDIGO]],'[1]Estrutura Loja'!$B$3:$M$2941,5,0) -> 3.4347817 | H26: =E26-G26 -> 0.56521832 | I26: 4 | J26: =(Tabela25[[#This Row],[PREÇO PRATICADO]]-((Tabela25[[#This Row],[PREÇO PRATICADO]])*([1]Informações!$H$6+[1]Informações!$H$15+[1]Informações!$H$19+[1]Informações!$H$20))-Tabela25[[#This Row],[CUSTO]])/Tabela25[[#This Row],[PREÇO PRATICADO]] -> 0.23928267 | K26: =Tabela25[[#This Row],[PREÇO PRATICADO]]*Tabela25[[#This Row],[LUCRO REAL %]] -> 0.95713069 | M26: =IF(Tabela25[[#This Row],[QUANT. VENDA]]=0,0,((Tabela25[[#This Row],[CUSTO]]*Tabela25[[#This Row],[QUANT. VENDA]])/(Tabela25[[#This Row],[QUANT. VENDA]]*Tabela25[[#This Row],[PREÇO PRATICADO]]))) -> 0 | N26: =VLOOKUP(Tabela25[[#This Row],[CÓDIGO]],'[1]Estrutura Loja'!$B$3:$E$1825,4,0) -> 0.95486931 | O26: =Tabela25[[#This Row],[QUANT. VENDA]]*Tabela25[[#This Row],[PREÇO PRATICADO]] -> 0 | P26: =Tabela25[[#This Row],[QUANT. VENDA]]*Tabela25[[#This Row],[CUSTO]] -> 0 | Q26: =Tabela25[[#This Row],[CUSTO]]/Tabela25[[#This Row],[PREÇO PRATICADO]] -> 0.23871733
A27: 140000020 | B27: 1014 | C27: Acai | D27: Ad Aç Granola | E27: 3 | F27: 3.5 | G27: =VLOOKUP(Tabela25[[#This Row],[CÓDIGO]],'[1]Estrutura Loja'!$B$3:$M$2941,5,0) -> 2.9810791 | H27: =E27-G27 -> 0.018920863 | I27: 3 | J27: =(Tabela25[[#This Row],[PREÇO PRATICADO]]-((Tabela25[[#This Row],[PREÇO PRATICADO]])*([1]Informações!$H$6+[1]Informações!$H$15+[1]Informações!$H$19+[1]Informações!$H$20))-Tabela25[[#This Row],[CUSTO]])/Tabela25[[#This Row],[PREÇO PRATICADO]] -> 0.20175333 | K27: =Tabela25[[#This Row],[PREÇO PRATICADO]]*Tabela25[[#This Row],[LUCRO REAL %]] -> 0.60526 | M27: =IF(Tabela25[[#This Row],[QUANT. VENDA]]=0,0,((Tabela25[[#This Row],[CUSTO]]*Tabela25[[#This Row],[QUANT. VENDA]])/(Tabela25[[#This Row],[QUANT. VENDA]]*Tabela25[[#This Row],[PREÇO PRATICADO]]))) -> 0 | N27: =VLOOKUP(Tabela25[[#This Row],[CÓDIGO]],'[1]Estrutura Loja'!$B$3:$E$1825,4,0) -> 0.82874 | O27: =Tabela25[[#This Row],[QUANT. VENDA]]*Tabela25[[#This Row],[PREÇO PRATICADO]] -> 0 | P27: =Tabela25[[#This Row],[QUANT. VENDA]]*Tabela25[[#This Row],[CUSTO]] -> 0 | Q27: =Tabela25[[#This Row],[CUSTO]]/Tabela25[[#This Row],[PREÇO PRATICADO]] -> 0.27624667
... A32: 140000025 | B32: 1014 | C32: Acai | D32: Ad Aç Ouro Branco | E32: 7.5 | F32: 7.5 | G32: =VLOOKUP(Tabela25[[#This Row],[CÓDIGO]],'[1]Estrutura Loja'!$B$3:$M$2941,5,0) -> 7.5876259 | H32: =E32-G32 -> -0.087625899 | I32: 7.5 | J32: =(Tabela25[[#This Row],[PREÇO PRATICADO]]-((Tabela25[[#This Row],[PREÇO PRATICADO]])*([1]Informações!$H$6+[1]Informações!$H$15+[1]Informações!$H$19+[1]Informações!$H$20))-Tabela25[[#This Row],[CUSTO]])/Tabela25[[#This Row],[PREÇO PRATICADO]] -> 0.196752 | K32: =Tabela25[[#This Row],[PREÇO PRATICADO]]*Tabela25[[#This Row],[LUCRO REAL %]] -> 1.47564 | M32: =IF(Tabela25[[#This Row],[QUANT. VENDA]]=0,0,((Tabela25[[#This Row],[CUSTO]]*Tabela25[[#This Row],[QUANT. VENDA]])/(Tabela25[[#This Row],[QUANT. VENDA]]*Tabela25[[#This Row],[PREÇO PRATICADO]]))) -> 0 | N32: =VLOOKUP(Tabela25[[#This Row],[CÓDIGO]],'[1]Estrutura Loja'!$B$3:$E$1825,4,0) -> 2.10936 | O32: =Tabela25[[#This Row],[QUANT. VENDA]]*Tabela25[[#This Row],[PREÇO PRATICADO]] -> 0 | P32: =Tabela25[[#This Row],[QUANT. VENDA]]*Tabela25[[#This Row],[CUSTO]] -> 0 | Q32: =Tabela25[[#This Row],[CUSTO]]/Tabela25[[#This Row],[PREÇO PRATICADO]] -> 0.281248
A33: 110000001 | B33: 1100 | C33: =VLOOKUP(Tabela25[[#This Row],[GRUPO]],[1]Produto!H180:I549,2,0) -> Adicional | D33: Ad Nutela | E33: 4.5 | F33: 5.5 | G33: =VLOOKUP(Tabela25[[#This Row],[CÓDIGO]],'[1]Estrutura Loja'!$B$3:$M$2941,5,0) -> 4.5627842 | H33: =E33-G33 -> -0.062784173 | I33: 4.5 | J33: =(Tabela25[[#This Row],[PREÇO PRATICADO]]-((Tabela25[[#This Row],[PREÇO PRATICADO]])*([1]Informações!$H$6+[1]Informações!$H$15+[1]Informações!$H$19+[1]Informações!$H$20))-Tabela25[[#This Row],[CUSTO]])/Tabela25[[#This Row],[PREÇO PRATICADO]] -> 0.19612133 | K33: =Tabela25[[#This Row],[PREÇO PRATICADO]]*Tabela25[[#This Row],[LUCRO REAL %]] -> 0.882546 | M33: =IF(Tabela25[[#This Row],[QUANT. VENDA]]=0,0,((Tabela25[[#This Row],[CUSTO]]*Tabela25[[#This Row],[QUANT. VENDA]])/(Tabela25[[#This Row],[QUANT. VENDA]]*Tabela25[[#This Row],[PREÇO PRATICADO]]))) -> 0 | N33: =VLOOKUP(Tabela25[[#This Row],[CÓDIGO]],'[1]Estrutura Loja'!$B$3:$E$1825,4,0) -> 1.268454 | O33: =Tabela25[[#This Row],[QUANT. VENDA]]*Tabela25[[#This Row],[PREÇO PRATICADO]] -> 0 | P33: =Tabela25[[#This Row],[QUANT. VENDA]]*Tabela25[[#This Row],[CUSTO]] -> 0 | Q33: =Tabela25[[#This Row],[CUSTO]]/Tabela25[[#This Row],[PREÇO PRATICADO]] -> 0.28187867
A34: 110000002 | B34: 1100 | C34: =VLOOKUP(Tabela25[[#This Row],[GRUPO]],[1]Produto!H181:I550,2,0) -> Adicional | D34: Ad Leite Ninho | E34: 3 | F34: 3 | G34: =VLOOKUP(Tabela25[[#This Row],[CÓDIGO]],'[1]Estrutura Loja'!$B$3:$M$2941,5,0) -> 2.2263789 | H34: =E34-G34 -> 0.7736211 | I34: 3 | J34: =(Tabela25[[#This Row],[PREÇO PRATICADO]]-((Tabela25[[#This Row],[PREÇO PRATICADO]])*([1]Informações!$H$6+[1]Informações!$H$15+[1]Informações!$H$19+[1]Informações!$H$20))-Tabela25[[#This Row],[CUSTO]])/Tabela25[[#This Row],[PREÇO PRATICADO]] -> 0.27168889 | K34: =Tabela25[[#This Row],[PREÇO PRATICADO]]*Tabela25[[#This Row],[LUCRO REAL %]] -> 0.81506667 | M34: =IF(Tabela25[[#This Row],[QUANT. VENDA]]=0,0,((Tabela25[[#This Row],[CUSTO]]*Tabela25[[#This Row],[QUANT. VENDA]])/(Tabela25[[#This Row],[QUANT. VENDA]]*Tabela25[[#This Row],[PREÇO PRATICADO]]))) -> 0 | N34: =VLOOKUP(Tabela25[[#This Row],[CÓDIGO]],'[1]Estrutura Loja'!$B$3:$E$1825,4,0) -> 0.61893333 | O34: =Tabela25[[#This Row],[QUANT. VENDA]]*Tabela25[[#This Row],[PREÇO PRATICADO]] -> 0 | P34: =Tabela25[[#This Row],[QUANT. VENDA]]*Tabela25[[#This Row],[CUSTO]] -> 0 | Q34: =Tabela25[[#This Row],[CUSTO]]/Tabela25[[#This Row],[PREÇO PRATICADO]] -> 0.20631111
A35: 110000003 | B35: 1100 | C35: =VLOOKUP(Tabela25[[#This Row],[GRUPO]],[1]Produto!H183:I552,2,0) -> Adicional | D35: Ad Chantilly | E35: 2 | F35: 2.5 | G35: =VLOOKUP(Tabela25[[#This Row],[CÓDIGO]],'[1]Estrutura Loja'!$B$3:$M$2941,5,0) -> 2.2509521 | H35: =E35-G35 -> -0.25095213 | I35: 2 | J35: =(Tabela25[[#This Row],[PREÇO PRATICADO]]-((Tabela25[[#This Row],[PREÇO PRATICADO]])*([1]Informações!$H$6+[1]Informações!$H$15+[1]Informações!$H$19+[1]Informações!$H$20))-Tabela25[[#This Row],[CUSTO]])/Tabela25[[#This Row],[PREÇO PRATICADO]] -> 0.16511765 | K35: =Tabela25[[#This Row],[PREÇO PRATICADO]]*Tabela25[[#This Row],[LUCRO REAL %]] -> 0.33023531 | M35: =IF(Tabela25[[#This Row],[QUANT. VENDA]]=0,0,((Tabela25[[#This Row],[CUSTO]]*Tabela25[[#This Row],[QUANT. VENDA]])/(Tabela25[[#This Row],[QUANT. VENDA]]*Tabela25[[#This Row],[PREÇO PRATICADO]]))) -> 0 | N35: =VLOOKUP(Tabela25[[#This Row],[CÓDIGO]],'[1]Estrutura Loja'!$B$3:$E$1825,4,0) -> 0.62576469 | O35: =Tabela25[[#This Row],[QUANT. VENDA]]*Tabela25[[#This Row],[PREÇO PRATICADO]] -> 0 | P35: =Tabela25[[#This Row],[QUANT. VENDA]]*Tabela25[[#This Row],[CUSTO]] -> 0 | Q35: =Tabela25[[#This Row],[CUSTO]]/Tabela25[[#This Row],[PREÇO PRATICADO]] -> 0.31288235
A36: 110000004 | B36: 1100 | C36: =VLOOKUP(Tabela25[[#This Row],[GRUPO]],[1]Produto!H184:I553,2,0) -> Adicional | D36: Ad Ganache Chiquinho | E36: 4 | F36: 5 | G36: =VLOOKUP(Tabela25[[#This Row],[CÓDIGO]],'[1]Estrutura Loja'!$B$3:$M$2941,5,0) -> 4.4751799 | H36: =E36-G36 -> -0.47517986 | I36: 4 | J36: =(Tabela25[[#This Row],[PREÇO PRATICADO]]-((Tabela25[[#This Row],[PREÇO PRATICADO]])*([1]Informações!$H$6+[1]Informações!$H$15+[1]Informações!$H$19+[1]Informações!$H$20))-Tabela25[[#This Row],[CUSTO]])/Tabela25[[#This Row],[PREÇO PRATICADO]] -> 0.166975 | K36: =Tabela25[[#This Row],[PREÇO PRATICADO]]*Tabela25[[#This Row],[LUCRO REAL %]] -> 0.6679 | M36: =IF(Tabela25[[#This Row],[QUANT. VENDA]]=0,0,((Tabela25[[#This Row],[CUSTO]]*Tabela25[[#This Row],[QUANT. VENDA]])/(Tabela25[[#This Row],[QUANT. VENDA]]*Tabela25[[#This Row],[PREÇO PRATICADO]]))) -> 0 | N36: =VLOOKUP(Tabela25[[#This Row],[CÓDIGO]],'[1]Estrutura Loja'!$B$3:$E$1825,4,0) -> 1.2441 | O36: =Tabela25[[#This Row],[QUANT. VENDA]]*Tabela25[[#This Row],[PREÇO PRATICADO]] -> 0 | P36: =Tabela25[[#This Row],[QUANT. VENDA]]*Tabela25[[#This Row],[CUSTO]] -> 0 | Q36: =Tabela25[[#This Row],[CUSTO]]/Tabela25[[#This Row],[PREÇO PRATICADO]] -> 0.311025
A37: 110000005 | B37: 1100 | C37: =VLOOKUP(Tabela25[[#This Row],[GRUPO]],[1]Produto!H185:I554,2,0) -> Adicional | D37: Ad Stracciatela Meio amarga | E37: 2 | F37: 2 | G37: =VLOOKUP(Tabela25[[#This Row],[CÓDIGO]],'[1]Estrutura Loja'!$B$3:$M$2941,5,0) -> 2.2191187 | H37: =E37-G37 -> -0.21911871 | I37: 2 | J37: =(Tabela25[[#This Row],[PREÇO PRATICADO]]-((Tabela25[[#This Row],[PREÇO PRATICADO]])*([1]Informações!$H$6+[1]Informações!$H$15+[1]Informações!$H$19+[1]Informações!$H$20))-Tabela25[[#This Row],[CUSTO]])/Tabela25[[#This Row],[PREÇO PRATICADO]] -> 0.1695425 | K37: =Tabela25[[#This Row],[PREÇO PRATICADO]]*Tabela25[[#This Row],[LUCRO REAL %]] -> 0.339085 | M37: =IF(Tabela25[[#This Row],[QUANT. VENDA]]=0,0,((Tabela25[[#This Row],[CUSTO]]*Tabela25[[#This Row],[QUANT. VENDA]])/(Tabela25[[#This Row],[QUANT. VENDA]]*Tabela25[[#This Row],[PREÇO PRATICADO]]))) -> 0 | N37: =VLOOKUP(Tabela25[[#This Row],[CÓDIGO]],'[1]Estrutura Loja'!$B$3:$E$1825,4,0) -> 0.616915 | O37: =Tabela25[[#This Row],[QUANT. VENDA]]*Tabela25[[#This Row],[PREÇO PRATICADO]] -> 0 | P37: =Tabela25[[#This Row],[QUANT. VENDA]]*Tabela25[[#This Row],[CUSTO]] -> 0 | Q37: =Tabela25[[#This Row],[CUSTO]]/Tabela25[[#This Row],[PREÇO PRATICADO]] -> 0.3084575
A38: 110000006 | B38: 1100 | C38: =VLOOKUP(Tabela25[[#This Row],[GRUPO]],[1]Produto!H186:I555,2,0) -> Adicional | D38: Ad Chocolate Granulado | E38: 1.5 | F38: 3 | G38: =VLOOKUP(Tabela25[[#This Row],[CÓDIGO]],'[1]Estrutura Loja'!$B$3:$M$2941,5,0) -> 1.5278866 | H38: =E38-G38 -> -0.027886602 | I38: 1.5 | J38: =(Tabela25[[#This Row],[PREÇO PRATICADO]]-((Tabela25[[#This Row],[PREÇO PRATICADO]])*([1]Informações!$H$6+[1]Informações!$H$15+[1]Informações!$H$19+[1]Informações!$H$20))-Tabela25[[#This Row],[CUSTO]])/Tabela25[[#This Row],[PREÇO PRATICADO]] -> 0.19483168 | K38: =Tabela25[[#This Row],[PREÇO PRATICADO]]*Tabela25[[#This Row],[LUCRO REAL %]] -> 0.29224752 | M38: =IF(Tabela25[[#This Row],[QUANT. VENDA]]=0,0,((Tabela25[[#This Row],[CUSTO]]*Tabela25[[#This Row],[QUANT. VENDA]])/(Tabela25[[#This Row],[QUANT. VENDA]]*Tabela25[[#This Row],[PREÇO PRATICADO]]))) -> 0 | N38: =VLOOKUP(Tabela25[[#This Row],[CÓDIGO]],'[1]Estrutura Loja'!$B$3:$E$1825,4,0) -> 0.42475248 | O38: =Tabela25[[#This Row],[QUANT. VENDA]]*Tabela25[[#This Row],[PREÇO PRATICADO]] -> 0 | P38: =Tabela25[[#This Row],[QUANT. VENDA]]*Tabela25[[#This Row],[CUSTO]] -> 0 | Q38: =Tabela25[[#This Row],[CUSTO]]/Tabela25[[#This Row],[PREÇO PRATICADO]] -> 0.28316832
A39: 110000007 | B39: 1100 | C39: =VLOOKUP(Tabela25[[#This Row],[GRUPO]],[1]Produto!H187:I556,2,0) -> Adicional | D39: Ad Cappuccino | E39: 2.5 | F39: 3 | G39: =VLOOKUP(Tabela25[[#This Row],[CÓDIGO]],'[1]Estrutura Loja'!$B$3:$M$2941,5,0) -> 3.1043345 | H39: =E39-G39 -> -0.60433453 | I39: 2.5 | J39: =(Tabela25[[#This Row],[PREÇO PRATICADO]]-((Tabela25[[#This Row],[PREÇO PRATICADO]])*([1]Informações!$H$6+[1]Informações!$H$15+[1]Informações!$H$19+[1]Informações!$H$20))-Tabela25[[#This Row],[CUSTO]])/Tabela25[[#This Row],[PREÇO PRATICADO]] -> 0.132798 | K39: =Tabela25[[#This Row],[PREÇO PRATICADO]]*Tabela25[[#This Row],[LUCRO REAL %]] -> 0.331995 | M39: =IF(Tabela25[[#This Row],[QUANT. VENDA]]=0,0,((Tabela25[[#This Row],[CUSTO]]*Tabela25[[#This Row],[QUANT. VENDA]])/(Tabela25[[#This Row],[QUANT. VENDA]]*Tabela25[[#This Row],[PREÇO PRATICADO]]))) -> 0 | N39: =VLOOKUP(Tabela25[[#This Row],[CÓDIGO]],'[1]Estrutura Loja'!$B$3:$E$1825,4,0) -> 0.863005 | O39: =Tabela25[[#This Row],[QUANT. VENDA]]*Tabela25[[#This Row],[PREÇO PRATICADO]] -> 0 | P39: =Tabela25[[#This Row],[QUANT. VENDA]]*Tabela25[[#This Row],[CUSTO]] -> 0 | Q39: =Tabela25[[#This Row],[CUSTO]]/Tabela25[[#This Row],[PREÇO PRATICADO]] -> 0.345202
A40: 110000008 | B40: 1100 | C40: =VLOOKUP(Tabela25[[#This Row],[GRUPO]],[1]Produto!H188:I557,2,0) -> Adicional | D40: Ad stracciatela Branca | E40: 2 | F40: 2 | G40: =VLOOKUP(Tabela25[[#This Row],[CÓDIGO]],'[1]Estrutura Loja'!$B$3:$M$2941,5,0) -> 2.6701439 | H40: =E40-G40 -> -0.67014388 | I40: 2 | J40: =(Tabela25[[#This Row],[PREÇO PRATICADO]]-((Tabela25[[#This Row],[PREÇO PRATICADO]])*([1]Informações!$H$6+[1]Informações!$H$15+[1]Informações!$H$19+[1]Informações!$H$20))-Tabela25[[#This Row],[CUSTO]])/Tabela25[[#This Row],[PREÇO PRATICADO]] -> 0.10685 | K40: =Tabela25[[#This Row],[PREÇO PRATICADO]]*Tabela25[[#This Row],[LUCRO REAL %]] -> 0.2137 | M40: =IF(Tabela25[[#This Row],[QUANT. VENDA]]=0,0,((Tabela25[[#This Row],[CUSTO]]*Tabela25[[#This Row],[QUANT. VENDA]])/(Tabela25[[#This Row],[QUANT. VENDA]]*Tabela25[[#This Row],[PREÇO PRATICADO]]))) -> 0 | N40: =VLOOKUP(Tabela25[[#This Row],[CÓDIGO]],'[1]Estrutura Loja'!$B$3:$E$1825,4,0) -> 0.7423 | O40: =Tabela25[[#This Row],[QUANT. VENDA]]*Tabela25[[#This Row],[PREÇO PRATICADO]] -> 0 | P40: =Tabela25[[#This Row],[QUANT. VENDA]]*Tabela25[[#This Row],[CUSTO]] -> 0 | Q40: =Tabela25[[#This Row],[CUSTO]]/Tabela25[[#This Row],[PREÇO PRATICADO]] -> 0.37115
A41: 110000009 | B41: 1100 | C41: =VLOOKUP(Tabela25[[#This Row],[GRUPO]],[1]Produto!H189:I558,2,0) -> Adicional | D41: Ad Creme de Menta | E41: 1.5 | F41: 2 | G41: =VLOOKUP(Tabela25[[#This Row],[CÓDIGO]],'[1]Estrutura Loja'!$B$3:$M$2941,5,0) -> 1.4589928 | H41: =E41-G41 -> 0.041007194 | I41: 1.5 | J41: =(Tabela25[[#This Row],[PREÇO PRATICADO]]-((Tabela25[[#This Row],[PREÇO PRATICADO]])*([1]Informações!$H$6+[1]Informações!$H$15+[1]Informações!$H$19+[1]Informações!$H$20))-Tabela25[[#This Row],[CUSTO]])/Tabela25[[#This Row],[PREÇO PRATICADO]] -> 0.2076 | K41: =Tabela25[[#This Row],[PREÇO PRATICADO]]*Tabela25[[#This Row],[LUCRO REAL %]] -> 0.3114 | M41: =IF(Tabela25[[#This Row],[QUANT. VENDA]]=0,0,((Tabela25[[#This Row],[CUSTO]]*Tabela25[[#This Row],[QUANT. VENDA]])/(Tabela25[[#This Row],[QUANT. VENDA]]*Tabela25[[#This Row],[PREÇO PRATICADO]]))) -> 0 | N41: =VLOOKUP(Tabela25[[#This Row],[CÓDIGO]],'[1]Estrutura Loja'!$B$3:$E$1825,4,0) -> 0.4056 | O41: =Tabela25[[#This Row],[QUANT. VENDA]]*Tabela25[[#This Row],[PREÇO PRATICADO]] -> 0 | P41: =Tabela25[[#This Row],[QUANT. VENDA]]*Tabela25[[#This Row],[CUSTO]] -> 0 | Q41: =Tabela25[[#This Row],[CUSTO]]/Tabela25[[#This Row],[PREÇO PRATICADO]] -> 0.2704
A42: 110000010 | B42: 1100 | C42: =VLOOKUP(Tabela25[[#This Row],[GRUPO]],[1]Produto!H190:I559,2,0) -> Adicional | D42: Ad Ovomaltine | E42: 1.5 | F42: 3 | G42: =VLOOKUP(Tabela25[[#This Row],[CÓDIGO]],'[1]Estrutura Loja'!$B$3:$M$2941,5,0) -> 1.672211 | H42: =E42-G42 -> -0.17221103 | I42: 1.5 | J42: =(Tabela25[[#This Row],[PREÇO PRATICADO]]-((Tabela25[[#This Row],[PREÇO PRATICADO]])*([1]Informações!$H$6+[1]Informações!$H$15+[1]Informações!$H$19+[1]Informações!$H$20))-Tabela25[[#This Row],[CUSTO]])/Tabela25[[#This Row],[PREÇO PRATICADO]] -> 0.16808356 | K42: =Tabela25[[#This Row],[PREÇO PRATICADO]]*Tabela25[[#This Row],[LUCRO REAL %]] -> 0.25212533 | M42: =IF(Tabela25[[#This Row],[QUANT. VENDA]]=0,0,((Tabela25[[#This Row],[CUSTO]]*Tabela25[[#This Row],[QUANT. VENDA]])/(Tabela25[[#This Row],[QUANT. VENDA]]*Tabela25[[#This Row],[PREÇO PRATICADO]]))) -> 0 | N42: =VLOOKUP(Tabela25[[#This Row],[CÓDIGO]],'[1]Estrutura Loja'!$B$3:$E$1825,4,0) -> 0.46487467 | O42: =Tabela25[[#This Row],[QUANT. VENDA]]*Tabela25[[#This Row],[PREÇO PRATICADO]] -> 0 | P42: =Tabela25[[#This Row],[QUANT. VENDA]]*Tabela25[[#This Row],[CUSTO]] -> 0 | Q42: =Tabela25[[#This Row],[CUSTO]]/Tabela25[[#This Row],[PREÇO PRATICADO]] -> 0.30991644
A43: 110000011 | B43: 1100 | C43: =VLOOKUP(Tabela25[[#This Row],[GRUPO]],[1]Produto!H191:I560,2,0) -> Adicional | D43: Ad Doce De Leite | E43: 2 | F43: 2 | G43: =VLOOKUP(Tabela25[[#This Row],[CÓDIGO]],'[1]Estrutura Loja'!$B$3:$M$2941,5,0) -> 1.1767873 | H43: =E43-G43 -> 0.82321268 | I43: 2 | J43: =(Tabela25[[#This Row],[PREÇO PRATICADO]]-((Tabela25[[#This Row],[PREÇO PRATICADO]])*([1]Informações!$H$6+[1]Informações!$H$15+[1]Informações!$H$19+[1]Informações!$H$20))-Tabela25[[#This Row],[CUSTO]])/Tabela25[[#This Row],[PREÇO PRATICADO]] -> 0.31442656 | K43: =Tabela25[[#This Row],[PREÇO PRATICADO]]*Tabela25[[#This Row],[LUCRO REAL %]] -> 0.62885313 | M43: =IF(Tabela25[[#This Row],[QUANT. VENDA]]=0,0,((Tabela25[[#This Row],[CUSTO]]*Tabela25[[#This Row],[QUANT. VENDA]])/(Tabela25[[#This Row],[QUANT. VENDA]]*Tabela25[[#This Row],[PREÇO PRATICADO]]))) -> 0 | N43: =VLOOKUP(Tabela25[[#This Row],[CÓDIGO]],'[1]Estrutura Loja'!$B$3:$E$1825,4,0) -> 0.32714688 | O43: =Tabela25[[#This Row],[QUANT. VENDA]]*Tabela25[[#This Row],[PREÇO PRATICADO]] -> 0 | P43: =Tabela25[[#This Row],[QUANT. VENDA]]*Tabela25[[#This Row],[CUSTO]] -> 0 | Q43: =Tabela25[[#This Row],[CUSTO]]/Tabela25[[#This Row],[PREÇO PRATICADO]] -> 0.16357344
A44: 110000012 | B44: 1100 | C44: =VLOOKUP(Tabela25[[#This Row],[GRUPO]],[1]Produto!H193:I561,2,0) -> Adicional | D44: Ad Calda Trufada | E44: 2.5 | F44: 3 | G44: =VLOOKUP(Tabela25[[#This Row],[CÓDIGO]],'[1]Estrutura Loja'!$B$3:$M$2941,5,0) -> 2.4049332 | H44: =E44-G44 -> 0.095066804 | I44: 2.5 | J44: =(Tabela25[[#This Row],[PREÇO PRATICADO]]-((Tabela25[[#This Row],[PREÇO PRATICADO]])*([1]Informações!$H$6+[1]Informações!$H$15+[1]Informações!$H$19+[1]Informações!$H$20))-Tabela25[[#This Row],[CUSTO]])/Tabela25[[#This Row],[PREÇO PRATICADO]] -> 0.21057143 | K44: =Tabela25[[#This Row],[PREÇO PRATICADO]]*Tabela25[[#This Row],[LUCRO REAL %]] -> 0.52642857 | M44: =IF(Tabela25[[#This Row],[QUANT. VENDA]]=0,0,((Tabela25[[#This Row],[CUSTO]]*Tabela25[[#This Row],[QUANT. VENDA]])/(Tabela25[[#This Row],[QUANT. VENDA]]*Tabela25[[#This Row],[PREÇO PRATICADO]]))) -> 0 | N44: =VLOOKUP(Tabela25[[#This Row],[CÓDIGO]],'[1]Estrutura Loja'!$B$3:$E$1825,4,0) -> 0.66857143 | O44: =Tabela25[[#This Row],[QUANT. VENDA]]*Tabela25[[#This Row],[PREÇO PRATICADO]] -> 0 | P44: =Tabela25[[#This Row],[QUANT. VENDA]]*Tabela25[[#This Row],[CUSTO]] -> 0 | Q44: =Tabela25[[#This Row],[CUSTO]]/Tabela25[[#This Row],[PREÇO PRATICADO]] -> 0.26742857
A45: 110000013 | B45: 1100 | C45: =VLOOKUP(Tabela25[[#This Row],[GRUPO]],[1]Produto!H196:I563,2,0) -> Adicional | D45: Ad Suco de limão | E45: 1.5 | F45: 3 | G45: =VLOOKUP(Tabela25[[#This Row],[CÓDIGO]],'[1]Estrutura Loja'!$B$3:$M$2941,5,0) -> 0.91726619 | H45: =E45-G45 -> 0.58273381 | I45: 1.5 | J45: =(Tabela25[[#This Row],[PREÇO PRATICADO]]-((Tabela25[[#This Row],[PREÇO PRATICADO]])*([1]Informações!$H$6+[1]Informações!$H$15+[1]Informações!$H$19+[1]Informações!$H$20))-Tabela25[[#This Row],[CUSTO]])/Tabela25[[#This Row],[PREÇO PRATICADO]] -> 0.308 | K45: =Tabela25[[#This Row],[PREÇO PRATICADO]]*Tabela25[[#This Row],[LUCRO REAL %]] -> 0.462 | M45: =IF(Tabela25[[#This Row],[QUANT. VENDA]]=0,0,((Tabela25[[#This Row],[CUSTO]]*Tabela25[[#This Row],[QUANT. VENDA]])/(Tabela25[[#This Row],[QUANT. VENDA]]*Tabela25[[#This Row],[PREÇO PRATICADO]]))) -> 0 | N45: =VLOOKUP(Tabela25[[#This Row],[CÓDIGO]],'[1]Estrutura Loja'!$B$3:$E$1825,4,0) -> 0.255 | O45: =Tabela25[[#This Row],[QUANT. VENDA]]*Tabela25[[#This Row],[PREÇO PRATICADO]] -> 0 | P45: =Tabela25[[#This Row],[QUANT. VENDA]]*Tabela25[[#This Row],[CUSTO]] -> 0 | Q45: =Tabela25[[#This Row],[CUSTO]]/Tabela25[[#This Row],[PREÇO PRATICADO]] -> 0.17
A46: 110000014 | B46: 1100 | C46: =VLOOKUP(Tabela25[[#This Row],[GRUPO]],[1]Produto!H197:I564,2,0) -> Adicional | D46: Ad Farinha Láctea | E46: 2 | F46: 2.5 | G46: =VLOOKUP(Tabela25[[#This Row],[CÓDIGO]],'[1]Estrutura Loja'!$B$3:$M$2941,5,0) -> 1.6246763 | H46: =E46-G46 -> 0.37532374 | I46: 2 | J46: =(Tabela25[[#This Row],[PREÇO PRATICADO]]-((Tabela25[[#This Row],[PREÇO PRATICADO]])*([1]Informações!$H$6+[1]Informações!$H$15+[1]Informações!$H$19+[1]Informações!$H$20))-Tabela25[[#This Row],[CUSTO]])/Tabela25[[#This Row],[PREÇO PRATICADO]] -> 0.25217 | K46: =Tabela25[[#This Row],[PREÇO PRATICADO]]*Tabela25[[#This Row],[LUCRO REAL %]] -> 0.50434 | M46: =IF(Tabela25[[#This Row],[QUANT. VENDA]]=0,0,((Tabela25[[#This Row],[CUSTO]]*Tabela25[[#This Row],[QUANT. VENDA]])/(Tabela25[[#This Row],[QUANT. VENDA]]*Tabela25[[#This Row],[PREÇO PRATICADO]]))) -> 0 | N46: =VLOOKUP(Tabela25[[#This Row],[CÓDIGO]],'[1]Estrutura Loja'!$B$3:$E$1825,4,0) -> 0.45166 | O46: =Tabela25[[#This Row],[QUANT. VENDA]]*Tabela25[[#This Row],[PREÇO PRATICADO]] -> 0 | P46: =Tabela25[[#This Row],[QUANT. VENDA]]*Tabela25[[#This Row],[CUSTO]] -> 0 | Q46: =Tabela25[[#This Row],[CUSTO]]/Tabela25[[#This Row],[PREÇO PRATICADO]] -> 0.22583
A47: 110000015 | B47: 1100 | C47: =VLOOKUP(Tabela25[[#This Row],[GRUPO]],[1]Produto!H199:I566,2,0) -> Adicional | D47: Ad Banana | E47: 1 | F47: 2 | G47: =VLOOKUP(Tabela25[[#This Row],[CÓDIGO]],'[1]Estrutura Loja'!$B$3:$M$2941,5,0) -> 0.45928058 | H47: =E47-G47 -> 0.54071942 | I47: 1 | J47: =(Tabela25[[#This Row],[PREÇO PRATICADO]]-((Tabela25[[#This Row],[PREÇO PRATICADO]])*([1]Informações!$H$6+[1]Informações!$H$15+[1]Informações!$H$19+[1]Informações!$H$20))-Tabela25[[#This Row],[CUSTO]])/Tabela25[[#This Row],[PREÇO PRATICADO]] -> 0.35032 | K47: =Tabela25[[#This Row],[PREÇO PRATICADO]]*Tabela25[[#This Row],[LUCRO REAL %]] -> 0.35032 | M47: =IF(Tabela25[[#This Row],[QUANT. VENDA]]=0,0,((Tabela25[[#This Row],[CUSTO]]*Tabela25[[#This Row],[QUANT. VENDA]])/(Tabela25[[#This Row],[QUANT. VENDA]]*Tabela25[[#This Row],[PREÇO PRATICADO]]))) -> 0 | N47: =VLOOKUP(Tabela25[[#This Row],[CÓDIGO]],'[1]Estrutura Loja'!$B$3:$E$1825,4,0) -> 0.12768 | O47: =Tabela25[[#This Row],[QUANT. VENDA]]*Tabela25[[#This Row],[PREÇO PRATICADO]] -> 0 | P47: =Tabela25[[#This Row],[QUANT. VENDA]]*Tabela25[[#This Row],[CUSTO]] -> 0 | Q47: =Tabela25[[#This Row],[CUSTO]]/Tabela25[[#This Row],[PREÇO PRATICADO]] -> 0.12768
A48: 110000016 | B48: 1100 | C48: =VLOOKUP(Tabela25[[#This Row],[GRUPO]],[1]Produto!H201:I568,2,0) -> Adicional | D48: Ad Mescla Frutas Vermelhas | E48: 4 | F48: 4 | G48: =VLOOKUP(Tabela25[[#This Row],[CÓDIGO]],'[1]Estrutura Loja'!$B$3:$M$2941,5,0) -> 3.8859712 | H48: =E48-G48 -> 0.11402878 | I48: 4 | J48: =(Tabela25[[#This Row],[PREÇO PRATICADO]]-((Tabela25[[#This Row],[PREÇO PRATICADO]])*([1]Informações!$H$6+[1]Informações!$H$15+[1]Informações!$H$19+[1]Informações!$H$20))-Tabela25[[#This Row],[CUSTO]])/Tabela25[[#This Row],[PREÇO PRATICADO]] -> 0.207925 | K48: =Tabela25[[#This Row],[PREÇO PRATICADO]]*Tabela25[[#This Row],[LUCRO REAL %]] -> 0.8317 | M48: =IF(Tabela25[[#This Row],[QUANT. VENDA]]=0,0,((Tabela25[[#This Row],[CUSTO]]*Tabela25[[#This Row],[QUANT. VENDA]])/(Tabela25[[#This Row],[QUANT. VENDA]]*Tabela25[[#This Row],[PREÇO PRATICADO]]))) -> 0 | N48: =VLOOKUP(Tabela25[[#This Row],[CÓDIGO]],'[1]Estrutura Loja'!$B$3:$E$1825,4,0) -> 1.0803 | O48: =Tabela25[[#This Row],[QUANT. VENDA]]*Tabela25[[#This Row],[PREÇO PRATICADO]] -> 0 | P48: =Tabela25[[#This Row],[QUANT. VENDA]]*Tabela25[[#This Row],[CUSTO]] -> 0 | Q48: =Tabela25[[#This Row],[CUSTO]]/Tabela25[[#This Row],[PREÇO PRATICADO]] -> 0.270075
A49: 110000017 | B49: 1100 | C49: =VLOOKUP(Tabela25[[#This Row],[GRUPO]],[1]Produto!H204:I569,2,0) -> Adicional | D49: Ad Mescla Maracuja | E49: 3 | F49: 3 | G49: =VLOOKUP(Tabela25[[#This Row],[CÓDIGO]],'[1]Estrutura Loja'!$B$3:$M$2941,5,0) -> 2.9059609 | H49: =E49-G49 -> 0.094039054 | I49: 3 | J49: =(Tabela25[[#This Row],[PREÇO PRATICADO]]-((Tabela25[[#This Row],[PREÇO PRATICADO]])*([1]Informações!$H$6+[1]Informações!$H$15+[1]Informações!$H$19+[1]Informações!$H$20))-Tabela25[[#This Row],[CUSTO]])/Tabela25[[#This Row],[PREÇO PRATICADO]] -> 0.20871429 | K49: =Tabela25[[#This Row],[PREÇO PRATICADO]]*Tabela25[[#This Row],[LUCRO REAL %]] -> 0.62614286 | M49: =IF(Tabela25[[#This Row],[QUANT. VENDA]]=0,0,((Tabela25[[#This Row],[CUSTO]]*Tabela25[[#This Row],[QUANT. VENDA]])/(Tabela25[[#This Row],[QUANT. VENDA]]*Tabela25[[#This Row],[PREÇO PRATICADO]]))) -> 0 | N49: =VLOOKUP(Tabela25[[#This Row],[CÓDIGO]],'[1]Estrutura Loja'!$B$3:$E$1825,4,0) -> 0.80785714 | O49: =Tabela25[[#This Row],[QUANT. VENDA]]*Tabela25[[#This Row],[PREÇO PRATICADO]] -> 0 | P49: =Tabela25[[#This Row],[QUANT. VENDA]]*Tabela25[[#This Row],[CUSTO]] -> 0 | Q49: =Tabela25[[#This Row],[CUSTO]]/Tabela25[[#This Row],[PREÇO PRATICADO]] -> 0.26928571
A50: 110000018 | B50: 1100 | C50: =VLOOKUP(Tabela25[[#This Row],[GRUPO]],[1]Produto!H205:I570,2,0) -> Adicional | D50: Ad Mescla Morango | E50: 3.5 | F50: 4 | G50: =VLOOKUP(Tabela25[[#This Row],[CÓDIGO]],'[1]Estrutura Loja'!$B$3:$M$2941,5,0) -> 3.4751285 | H50: =E50-G50 -> 0.024871531 | I50: 3.5 | J50: =(Tabela25[[#This Row],[PREÇO PRATICADO]]-((Tabela25[[#This Row],[PREÇO PRATICADO]])*([1]Informações!$H$6+[1]Informações!$H$15+[1]Informações!$H$19+[1]Informações!$H$20))-Tabela25[[#This Row],[CUSTO]])/Tabela25[[#This Row],[PREÇO PRATICADO]] -> 0.20197551 | K50: =Tabela25[[#This Row],[PREÇO PRATICADO]]*Tabela25[[#This Row],[LUCRO REAL %]] -> 0.70691429 | M50: =IF(Tabela25[[#This Row],[QUANT. VENDA]]=0,0,((Tabela25[[#This Row],[CUSTO]]*Tabela25[[#This Row],[QUANT. VENDA]])/(Tabela25[[#This Row],[QUANT. VENDA]]*Tabela25[[#This Row],[PREÇO PRATICADO]]))) -> 0 | N50: =VLOOKUP(Tabela25[[#This Row],[CÓDIGO]],'[1]Estrutura Loja'!$B$3:$E$1825,4,0) -> 0.96608571 | O50: =Tabela25[[#This Row],[QUANT. VENDA]]*Tabela25[[#This Row],[PREÇO PRATICADO]] -> 0 | P50: =Tabela25[[#This Row],[QUANT. VENDA]]*Tabela25[[#This Row],[CUSTO]] -> 0 | Q50: =Tabela25[[#This Row],[CUSTO]]/Tabela25[[#This Row],[PREÇO PRATICADO]] -> 0.27602449
A51: 110000019 | B51: 1100 | C51: =VLOOKUP(Tabela25[[#This Row],[GRUPO]],[1]Produto!H207:I572,2,0) -> Adicional | D51: Ad Leite Condensado | E51: 3 | F51: 4 | G51: =VLOOKUP(Tabela25[[#This Row],[CÓDIGO]],'[1]Estrutura Loja'!$B$3:$M$2941,5,0) -> 2.5268646 | H51: =E51-G51 -> 0.47313542 | I51: 3 | J51: =(Tabela25[[#This Row],[PREÇO PRATICADO]]-((Tabela25[[#This Row],[PREÇO PRATICADO]])*([1]Informações!$H$6+[1]Informações!$H$15+[1]Informações!$H$19+[1]Informações!$H$20))-Tabela25[[#This Row],[CUSTO]])/Tabela25[[#This Row],[PREÇO PRATICADO]] -> 0.24384388 | K51: =Tabela25[[#This Row],[PREÇO PRATICADO]]*Tabela25[[#This Row],[LUCRO REAL %]] -> 0.73153165 | M51: =IF(Tabela25[[#This Row],[QUANT. VENDA]]=0,0,((Tabela25[[#This Row],[CUSTO]]*Tabela25[[#This Row],[QUANT. VENDA]])/(Tabela25[[#This Row],[QUANT. VENDA]]*Tabela25[[#This Row],[PREÇO PRATICADO]]))) -> 0 | N51: =VLOOKUP(Tabela25[[#This Row],[CÓDIGO]],'[1]Estrutura Loja'!$B$3:$E$1825,4,0) -> 0.70246835 | O51: =Tabela25[[#This Row],[QUANT. VENDA]]*Tabela25[[#This Row],[PREÇO PRATICADO]] -> 0 | P51: =Tabela25[[#This Row],[QUANT. VENDA]]*Tabela25[[#This Row],[CUSTO]] -> 0 | Q51: =Tabela25[[#This Row],[CUSTO]]/Tabela25[[#This Row],[PREÇO PRATICADO]] -> 0.23415612
A52: 110000020 | B52: 1100 | C52: =VLOOKUP(Tabela25[[#This Row],[GRUPO]],[1]Produto!H208:I573,2,0) -> Adicional | D52: Ad Suflair (30g) | E52: 9 | F52: 10 | G52: =VLOOKUP(Tabela25[[#This Row],[CÓDIGO]],'[1]Estrutura Loja'!$B$3:$M$2941,5,0) -> 12.592703 | H52: =E52-G52 -> -3.5927032 | I52: 9 | J52: =(Tabela25[[#This Row],[PREÇO PRATICADO]]-((Tabela25[[#This Row],[PREÇO PRATICADO]])*([1]Informações!$H$6+[1]Informações!$H$15+[1]Informações!$H$19+[1]Informações!$H$20))-Tabela25[[#This Row],[CUSTO]])/Tabela25[[#This Row],[PREÇO PRATICADO]] -> 0.089025391 | K52: =Tabela25[[#This Row],[PREÇO PRATICADO]]*Tabela25[[#This Row],[LUCRO REAL %]] -> 0.80122852 | M52: =IF(Tabela25[[#This Row],[QUANT. VENDA]]=0,0,((Tabela25[[#This Row],[CUSTO]]*Tabela25[[#This Row],[QUANT. VENDA]])/(Tabela25[[#This Row],[QUANT. VENDA]]*Tabela25[[#This Row],[PREÇO PRATICADO]]))) -> 0 | N52: =VLOOKUP(Tabela25[[#This Row],[CÓDIGO]],'[1]Estrutura Loja'!$B$3:$E$1825,4,0) -> 3.5007715 | O52: =Tabela25[[#This Row],[QUANT. VENDA]]*Tabela25[[#This Row],[PREÇO PRATICADO]] -> 0 | P52: =Tabela25[[#This Row],[QUANT. VENDA]]*Tabela25[[#This Row],[CUSTO]] -> 0 | Q52: =Tabela25[[#This Row],[CUSTO]]/Tabela25[[#This Row],[PREÇO PRATICADO]] -> 0.38897461
A53: 110000021 | B53: 1100 | C53: =VLOOKUP(Tabela25[[#This Row],[GRUPO]],[1]Produto!H209:I574,2,0) -> Adicional | D53: Ad Suflair (20g) | E53: 6 | F53: 7 | G53: =VLOOKUP(Tabela25[[#This Row],[CÓDIGO]],'[1]Estrutura Loja'!$B$3:$M$2941,5,0) -> 8.3951355 | H53: =E53-G53 -> -2.3951355 | I53: 6 | J53: =(Tabela25[[#This Row],[PREÇO PRATICADO]]-((Tabela25[[#This Row],[PREÇO PRATICADO]])*([1]Informações!$H$6+[1]Informações!$H$15+[1]Informações!$H$19+[1]Informações!$H$20))-Tabela25[[#This Row],[CUSTO]])/Tabela25[[#This Row],[PREÇO PRATICADO]] -> 0.089025391 | K53: =Tabela25[[#This Row],[PREÇO PRATICADO]]*Tabela25[[#This Row],[LUCRO REAL %]] -> 0.53415234 | M53: =IF(Tabela25[[#This Row],[QUANT. VENDA]]=0,0,((Tabela25[[#This Row],[CUSTO]]*Tabela25[[#This Row],[QUANT. VENDA]])/(Tabela25[[#This Row],[QUANT. VENDA]]*Tabela25[[#This Row],[PREÇO PRATICADO]]))) -> 0 | N53: =VLOOKUP(Tabela25[[#This Row],[CÓDIGO]],'[1]Estrutura Loja'!$B$3:$E$1825,4,0) -> 2.3338477 | O53: =Tabela25[[#This Row],[QUANT. VENDA]]*Tabela25[[#This Row],[PREÇO PRATICADO]] -> 0 | P53: =Tabela25[[#This Row],[QUANT. VENDA]]*Tabela25[[#This Row],[CUSTO]] -> 0 | Q53: =Tabela25[[#This Row],[CUSTO]]/Tabela25[[#This Row],[PREÇO PRATICADO]] -> 0.38897461
A54: 110000022 | B54: 1100 | C54: =VLOOKUP(Tabela25[[#This Row],[GRUPO]],[1]Produto!H51:I398,2,0) -> Adicional | D54: Ad Suflair Duo | E54: 9 | F54: 10 | G54: =VLOOKUP(Tabela25[[#This Row],[CÓDIGO]],'[1]Estrutura Loja'!$B$3:$M$2941,5,0) -> 12.592703 | H54: =E54-G54 -> -3.5927032 | I54: 9 | J54: =(Tabela25[[#This Row],[PREÇO PRATICADO]]-((Tabela25[[#This Row],[PREÇO PRATICADO]])*([1]Informações!$H$6+[1]Informações!$H$15+[1]Informações!$H$19+[1]Informações!$H$20))-Tabela25[[#This Row],[CUSTO]])/Tabela25[[#This Row],[PREÇO PRATICADO]] -> 0.089025391 | K54: =Tabela25[[#This Row],[PREÇO PRATICADO]]*Tabela25[[#This Row],[LUCRO REAL %]] -> 0.80122852 | M54: =IF(Tabela25[[#This Row],[QUANT. VENDA]]=0,0,((Tabela25[[#This Row],[CUSTO]]*Tabela25[[#This Row],[QUANT. VENDA]])/(Tabela25[[#This Row],[QUANT. VENDA]]*Tabela25[[#This Row],[PREÇO PRATICADO]]))) -> 0 | N54: =VLOOKUP(Tabela25[[#This Row],[CÓDIGO]],'[1]Estrutura Loja'!$B$3:$E$1825,4,0) -> 3.5007715 | O54: =Tabela25[[#This Row],[QUANT. VENDA]]*Tabela25[[#This Row],[PREÇO PRATICADO]] -> 0 | P54: =Tabela25[[#This Row],[QUANT. VENDA]]*Tabela25[[#This Row],[CUSTO]] -> 0 | Q54: =Tabela25[[#This Row],[CUSTO]]/Tabela25[[#This Row],[PREÇO PRATICADO]] -> 0.38897461
A55: 110000023 | B55: 1100 | C55: =VLOOKUP(Tabela25[[#This Row],[GRUPO]],[1]Produto!H215:I576,2,0) -> Adicional | D55: Ad Kit Kat | E55: 7 | F55: 7 | G55: =VLOOKUP(Tabela25[[#This Row],[CÓDIGO]],'[1]Estrutura Loja'!$B$3:$M$2941,5,0) -> 6.1522371 | H55: =E55-G55 -> 0.8477629 | I55: 7 | J55: =(Tabela25[[#This Row],[PREÇO PRATICADO]]-((Tabela25[[#This Row],[PREÇO PRATICADO]])*([1]Informações!$H$6+[1]Informações!$H$15+[1]Informações!$H$19+[1]Informações!$H$20))-Tabela25[[#This Row],[CUSTO]])/Tabela25[[#This Row],[PREÇO PRATICADO]] -> 0.2336683 | K55: =Tabela25[[#This Row],[PREÇO PRATICADO]]*Tabela25[[#This Row],[LUCRO REAL %]] -> 1.6356781 | M55: =IF(Tabela25[[#This Row],[QUANT. VENDA]]=0,0,((Tabela25[[#This Row],[CUSTO]]*Tabela25[[#This Row],[QUANT. VENDA]])/(Tabela25[[#This Row],[QUANT. VENDA]]*Tabela25[[#This Row],[PREÇO PRATICADO]]))) -> 0 | N55: =VLOOKUP(Tabela25[[#This Row],[CÓDIGO]],'[1]Estrutura Loja'!$B$3:$E$1825,4,0) -> 1.7103219 | O55: =Tabela25[[#This Row],[QUANT. VENDA]]*Tabela25[[#This Row],[PREÇO PRATICADO]] -> 0 | P55: =Tabela25[[#This Row],[QUANT. VENDA]]*Tabela25[[#This Row],[CUSTO]] -> 0 | Q55: =Tabela25[[#This Row],[CUSTO]]/Tabela25[[#This Row],[PREÇO PRATICADO]] -> 0.2443317
A56: 110000024 | B56: 1100 | C56: =VLOOKUP(Tabela25[[#This Row],[GRUPO]],[1]Produto!H216:I577,2,0) -> Adicional | D56: Ad Polpa de Maracujá | E56: 3 | F56: 4 | G56: =VLOOKUP(Tabela25[[#This Row],[CÓDIGO]],'[1]Estrutura Loja'!$B$3:$M$2941,5,0) -> 3.0510879 | H56: =E56-G56 -> -0.05108791 | I56: 3 | J56: =(Tabela25[[#This Row],[PREÇO PRATICADO]]-((Tabela25[[#This Row],[PREÇO PRATICADO]])*([1]Informações!$H$6+[1]Informações!$H$15+[1]Informações!$H$19+[1]Informações!$H$20))-Tabela25[[#This Row],[CUSTO]])/Tabela25[[#This Row],[PREÇO PRATICADO]] -> 0.19526585 | K56: =Tabela25[[#This Row],[PREÇO PRATICADO]]*Tabela25[[#This Row],[LUCRO REAL %]] -> 0.58579756 | M56: =IF(Tabela25[[#This Row],[QUANT. VENDA]]=0,0,((Tabela25[[#This Row],[CUSTO]]*Tabela25[[#This Row],[QUANT. VENDA]])/(Tabela25[[#This Row],[QUANT. VENDA]]*Tabela25[[#This Row],[PREÇO PRATICADO]]))) -> 0 | N56: =VLOOKUP(Tabela25[[#This Row],[CÓDIGO]],'[1]Estrutura Loja'!$B$3:$E$1825,4,0) -> 0.84820244 | O56: =Tabela25[[#This Row],[QUANT. VENDA]]*Tabela25[[#This Row],[PREÇO PRATICADO]] -> 0 | P56: =Tabela25[[#This Row],[QUANT. VENDA]]*Tabela25[[#This Row],[CUSTO]] -> 0 | Q56: =Tabela25[[#This Row],[CUSTO]]/Tabela25[[#This Row],[PREÇO PRATICADO]] -> 0.28273415
A57: 110000025 | B57: 1100 | C57: =VLOOKUP(Tabela25[[#This Row],[GRUPO]],[1]Produto!H217:I578,2,0) -> Adicional | D57: Ad Polpa de Morango | E57: 3 | F57: 4 | G57: =VLOOKUP(Tabela25[[#This Row],[CÓDIGO]],'[1]Estrutura Loja'!$B$3:$M$2941,5,0) -> 2.7968306 | H57: =E57-G57 -> 0.20316942 | I57: 3 | J57: =(Tabela25[[#This Row],[PREÇO PRATICADO]]-((Tabela25[[#This Row],[PREÇO PRATICADO]])*([1]Informações!$H$6+[1]Informações!$H$15+[1]Informações!$H$19+[1]Informações!$H$20))-Tabela25[[#This Row],[CUSTO]])/Tabela25[[#This Row],[PREÇO PRATICADO]] -> 0.21882703 | K57: =Tabela25[[#This Row],[PREÇO PRATICADO]]*Tabela25[[#This Row],[LUCRO REAL %]] -> 0.6564811 | M57: =IF(Tabela25[[#This Row],[QUANT. VENDA]]=0,0,((Tabela25[[#This Row],[CUSTO]]*Tabela25[[#This Row],[QUANT. VENDA]])/(Tabela25[[#This Row],[QUANT. VENDA]]*Tabela25[[#This Row],[PREÇO PRATICADO]]))) -> 0 | N57: =VLOOKUP(Tabela25[[#This Row],[CÓDIGO]],'[1]Estrutura Loja'!$B$3:$E$1825,4,0) -> 0.7775189 | O57: =Tabela25[[#This Row],[QUANT. VENDA]]*Tabela25[[#This Row],[PREÇO PRATICADO]] -> 0 | P57: =Tabela25[[#This Row],[QUANT. VENDA]]*Tabela25[[#This Row],[CUSTO]] -> 0 | Q57: =Tabela25[[#This Row],[CUSTO]]/Tabela25[[#This Row],[PREÇO PRATICADO]] -> 0.25917297
A58: 110000026 | B58: 1100 | C58: =VLOOKUP(Tabela25[[#This Row],[GRUPO]],[1]Produto!H218:I579,2,0) -> Adicional | D58: Ad Polpa de Frutas Vermelhas | E58: 3 | F58: 4 | G58: =VLOOKUP(Tabela25[[#This Row],[CÓDIGO]],'[1]Estrutura Loja'!$B$3:$M$2941,5,0) -> 3.5134673 | H58: =E58-G58 -> -0.51346727 | I58: 3 | J58: =(Tabela25[[#This Row],[PREÇO PRATICADO]]-((Tabela25[[#This Row],[PREÇO PRATICADO]])*([1]Informações!$H$6+[1]Informações!$H$15+[1]Informações!$H$19+[1]Informações!$H$20))-Tabela25[[#This Row],[CUSTO]])/Tabela25[[#This Row],[PREÇO PRATICADO]] -> 0.1524187 | K58: =Tabela25[[#This Row],[PREÇO PRATICADO]]*Tabela25[[#This Row],[LUCRO REAL %]] -> 0.4572561 | M58: =IF(Tabela25[[#This Row],[QUANT. VENDA]]=0,0,((Tabela25[[#This Row],[CUSTO]]*Tabela25[[#This Row],[QUANT. VENDA]])/(Tabela25[[#This Row],[QUANT. VENDA]]*Tabela25[[#This Row],[PREÇO PRATICADO]]))) -> 0 | N58: =VLOOKUP(Tabela25[[#This Row],[CÓDIGO]],'[1]Estrutura Loja'!$B$3:$E$1825,4,0) -> 0.9767439 | O58: =Tabela25[[#This Row],[QUANT. VENDA]]*Tabela25[[#This Row],[PREÇO PRATICADO]] -> 0 | P58: =Tabela25[[#This Row],[QUANT. VENDA]]*Tabela25[[#This Row],[CUSTO]] -> 0 | Q58: =Tabela25[[#This Row],[CUSTO]]/Tabela25[[#This Row],[PREÇO PRATICADO]] -> 0.3255813
A59: 110000027 | B59: 1100 | C59: =VLOOKUP(Tabela25[[#This Row],[GRUPO]],[1]Produto!H218:I581,2,0) -> Adicional | D59: Ad Biscoito Negresco (3 bisc.) | E59: 4 | F59: 5 | G59: =VLOOKUP(Tabela25[[#This Row],[CÓDIGO]],'[1]Estrutura Loja'!$B$3:$M$2941,5,0) -> 3.0161871 | H59: =E59-G59 -> 0.98381295 | I59: 4 | J59: =(Tabela25[[#This Row],[PREÇO PRATICADO]]-((Tabela25[[#This Row],[PREÇO PRATICADO]])*([1]Informações!$H$6+[1]Informações!$H$15+[1]Informações!$H$19+[1]Informações!$H$20))-Tabela25[[#This Row],[CUSTO]])/Tabela25[[#This Row],[PREÇO PRATICADO]] -> 0.268375 | K59: =Tabela25[[#This Row],[PREÇO PRATICADO]]*Tabela25[[#This Row],[LUCRO REAL %]] -> 1.0735 | M59: =IF(Tabela25[[#This Row],[QUANT. VENDA]]=0,0,((Tabela25[[#This Row],[CUSTO]]*Tabela25[[#This Row],[QUANT. VENDA]])/(Tabela25[[#This Row],[QUANT. VENDA]]*Tabela25[[#This Row],[PREÇO PRATICADO]]))) -> 0 | N59: =VLOOKUP(Tabela25[[#This Row],[CÓDIGO]],'[1]Estrutura Loja'!$B$3:$E$1825,4,0) -> 0.8385 | O59: =Tabela25[[#This Row],[QUANT. VENDA]]*Tabela25[[#This Row],[PREÇO PRATICADO]] -> 0 | P59: =Tabela25[[#This Row],[QUANT. VENDA]]*Tabela25[[#This Row],[CUSTO]] -> 0 | Q59: =Tabela25[[#This Row],[CUSTO]]/Tabela25[[#This Row],[PREÇO PRATICADO]] -> 0.209625
A60: 110000028 | B60: 1100 | C60: =VLOOKUP(Tabela25[[#This Row],[GRUPO]],[1]Produto!H219:I583,2,0) -> Adicional | D60: Ad Biscoito Negresco (2 bisc.) | E60: 2.5 | F60: 3.5 | G60: =VLOOKUP(Tabela25[[#This Row],[CÓDIGO]],'[1]Estrutura Loja'!$B$3:$M$2941,5,0) -> 2.0107914 | H60: =E60-G60 -> 0.48920863 | I60: 2.5 | J60: =(Tabela25[[#This Row],[PREÇO PRATICADO]]-((Tabela25[[#This Row],[PREÇO PRATICADO]])*([1]Informações!$H$6+[1]Informações!$H$15+[1]Informações!$H$19+[1]Informações!$H$20))-Tabela25[[#This Row],[CUSTO]])/Tabela25[[#This Row],[PREÇO PRATICADO]] -> 0.2544 | K60: =Tabela25[[#This Row],[PREÇO PRATICADO]]*Tabela25[[#This Row],[LUCRO REAL %]] -> 0.636 | M60: =IF(Tabela25[[#This Row],[QUANT. VENDA]]=0,0,((Tabela25[[#This Row],[CUSTO]]*Tabela25[[#This Row],[QUANT. VENDA]])/(Tabela25[[#This Row],[QUANT. VENDA]]*Tabela25[[#This Row],[PREÇO PRATICADO]]))) -> 0 | N60: =VLOOKUP(Tabela25[[#This Row],[CÓDIGO]],'[1]Estrutura Loja'!$B$3:$E$1825,4,0) -> 0.559 | O60: =Tabela25[[#This Row],[QUANT. VENDA]]*Tabela25[[#This Row],[PREÇO PRATICADO]] -> 0 | P60: =Tabela25[[#This Row],[QUANT. VENDA]]*Tabela25[[#This Row],[CUSTO]] -> 0 | Q60: =Tabela25[[#This Row],[CUSTO]]/Tabela25[[#This Row],[PREÇO PRATICADO]] -> 0.2236
A61: 110000029 | B61: 1100 | C61: =VLOOKUP(Tabela25[[#This Row],[GRUPO]],[1]Produto!H224:I584,2,0) -> Adicional | D61: Ad Bombom Ouro Branco (2 unid.) | E61: 7.5 | F61: 8.5 | G61: =VLOOKUP(Tabela25[[#This Row],[CÓDIGO]],'[1]Estrutura Loja'!$B$3:$M$2941,5,0) -> 7.5876259 | H61: =E61-G61 -> -0.087625899 | I61: 7.5 | J61: =(Tabela25[[#This Row],[PREÇO PRATICADO]]-((Tabela25[[#This Row],[PREÇO PRATICADO]])*([1]Informações!$H$6+[1]Informações!$H$15+[1]Informações!$H$19+[1]Informações!$H$20))-Tabela25[[#This Row],[CUSTO]])/Tabela25[[#This Row],[PREÇO PRATICADO]] -> 0.196752 | K61: =Tabela25[[#This Row],[PREÇO PRATICADO]]*Tabela25[[#This Row],[LUCRO REAL %]] -> 1.47564 | M61: =IF(Tabela25[[#This Row],[QUANT. VENDA]]=0,0,((Tabela25[[#This Row],[CUSTO]]*Tabela25[[#This Row],[QUANT. VENDA]])/(Tabela25[[#This Row],[QUANT. VENDA]]*Tabela25[[#This Row],[PREÇO PRATICADO]]))) -> 0 | N61: =VLOOKUP(Tabela25[[#This Row],[CÓDIGO]],'[1]Estrutura Loja'!$B$3:$E$1825,4,0) -> 2.10936 | O61: =Tabela25[[#This Row],[QUANT. VENDA]]*Tabela25[[#This Row],[PREÇO PRATICADO]] -> 0 | P61: =Tabela25[[#This Row],[QUANT. VENDA]]*Tabela25[[#This Row],[CUSTO]] -> 0 | Q61: =Tabela25[[#This Row],[CUSTO]]/Tabela25[[#This Row],[PREÇO PRATICADO]] -> 0.281248
A62: 110000030 | B62: 1100 | C62: =VLOOKUP(Tabela25[[#This Row],[GRUPO]],[1]Produto!H225:I585,2,0) -> Adicional | D62: Ad Bombom Ouro Branco (1 unid.) | E62: 4 | F62: 5 | G62: =VLOOKUP(Tabela25[[#This Row],[CÓDIGO]],'[1]Estrutura Loja'!$B$3:$M$2941,5,0) -> 3.7938129 | H62: =E62-G62 -> 0.20618705 | I62: 4 | J62: =(Tabela25[[#This Row],[PREÇO PRATICADO]]-((Tabela25[[#This Row],[PREÇO PRATICADO]])*([1]Informações!$H$6+[1]Informações!$H$15+[1]Informações!$H$19+[1]Informações!$H$20))-Tabela25[[#This Row],[CUSTO]])/Tabela25[[#This Row],[PREÇO PRATICADO]] -> 0.21433 | K62: =Tabela25[[#This Row],[PREÇO PRATICADO]]*Tabela25[[#This Row],[LUCRO REAL %]] -> 0.85732 | M62: =IF(Tabela25[[#This Row],[QUANT. VENDA]]=0,0,((Tabela25[[#This Row],[CUSTO]]*Tabela25[[#This Row],[QUANT. VENDA]])/(Tabela25[[#This Row],[QUANT. VENDA]]*Tabela25[[#This Row],[PREÇO PRATICADO]]))) -> 0 | N62: =VLOOKUP(Tabela25[[#This Row],[CÓDIGO]],'[1]Estrutura Loja'!$B$3:$E$1825,4,0) -> 1.05468 | O62: =Tabela25[[#This Row],[QUANT. VENDA]]*Tabela25[[#This Row],[PREÇO PRATICADO]] -> 0 | P62: =Tabela25[[#This Row],[QUANT. VENDA]]*Tabela25[[#This Row],[CUSTO]] -> 0 | Q62: =Tabela25[[#This Row],[CUSTO]]/Tabela25[[#This Row],[PREÇO PRATICADO]] -> 0.26367
A63: 110000031 | B63: 1100 | C63: =VLOOKUP(Tabela25[[#This Row],[GRUPO]],[1]Produto!H226:I586,2,0) -> Adicional | D63: Ad Açaí | E63: 4 | F63: 4 | G63: =VLOOKUP(Tabela25[[#This Row],[CÓDIGO]],'[1]Estrutura Loja'!$B$3:$M$2941,5,0) -> 3.0043651 | H63: =E63-G63 -> 0.99563489 | I63: 4 | J63: =(Tabela25[[#This Row],[PREÇO PRATICADO]]-((Tabela25[[#This Row],[PREÇO PRATICADO]])*([1]Informações!$H$6+[1]Informações!$H$15+[1]Informações!$H$19+[1]Informações!$H$20))-Tabela25[[#This Row],[CUSTO]])/Tabela25[[#This Row],[PREÇO PRATICADO]] -> 0.26919663 | K63: =Tabela25[[#This Row],[PREÇO PRATICADO]]*Tabela25[[#This Row],[LUCRO REAL %]] -> 1.0767865 | M63: =IF(Tabela25[[#This Row],[QUANT. VENDA]]=0,0,((Tabela25[[#This Row],[CUSTO]]*Tabela25[[#This Row],[QUANT. VENDA]])/(Tabela25[[#This Row],[QUANT. VENDA]]*Tabela25[[#This Row],[PREÇO PRATICADO]]))) -> 0 | N63: =VLOOKUP(Tabela25[[#This Row],[CÓDIGO]],'[1]Estrutura Loja'!$B$3:$E$1825,4,0) -> 0.8352135 | O63: =Tabela25[[#This Row],[QUANT. VENDA]]*Tabela25[[#This Row],[PREÇO PRATICADO]] -> 0 | P63: =Tabela25[[#This Row],[QUANT. VENDA]]*Tabela25[[#This Row],[CUSTO]] -> 0 | Q63: =Tabela25[[#This Row],[CUSTO]]/Tabela25[[#This Row],[PREÇO PRATICADO]] -> 0.20880337
A64: 110000032 | B64: 1100 | C64: =VLOOKUP(Tabela25[[#This Row],[GRUPO]],[1]Produto!H290:I592,2,0) -> Adicional | D64: Ad Creme Crocante Ovomaltine | E64: 4 | F64: 4 | G64: =VLOOKUP(Tabela25[[#This Row],[CÓDIGO]],'[1]Estrutura Loja'!$B$3:$M$2941,5,0) -> 3.7546403 | H64: =E64-G64 -> 0.24535971 | I64: 4 | J64: =(Tabela25[[#This Row],[PREÇO PRATICADO]]-((Tabela25[[#This Row],[PREÇO PRATICADO]])*([1]Informações!$H$6+[1]Informações!$H$15+[1]Informações!$H$19+[1]Informações!$H$20))-Tabela25[[#This Row],[CUSTO]])/Tabela25[[#This Row],[PREÇO PRATICADO]] -> 0.2170525 | K64: =Tabela25[[#This Row],[PREÇO PRATICADO]]*Tabela25[[#This Row],[LUCRO REAL %]] -> 0.86821 | M64: =IF(Tabela25[[#This Row],[QUANT. VENDA]]=0,0,((Tabela25[[#This Row],[CUSTO]]*Tabela25[[#This Row],[QUANT. VENDA]])/(Tabela25[[#This Row],[QUANT. VENDA]]*Tabela25[[#This Row],[PREÇO PRATICADO]]))) -> 0 | N64: =VLOOKUP(Tabela25[[#This Row],[CÓDIGO]],'[1]Estrutura Loja'!$B$3:$E$1825,4,0) -> 1.04379 | O64: =Tabela25[[#This Row],[QUANT. VENDA]]*Tabela25[[#This Row],[PREÇO PRATICADO]] -> 0 | P64: =Tabela25[[#This Row],[QUANT. VENDA]]*Tabela25[[#This Row],[CUSTO]] -> 0 | Q64: =Tabela25[[#This Row],[CUSTO]]/Tabela25[[#This Row],[PREÇO PRATICADO]] -> 0.2609475
A65: 110000033 | B65: 1100 | C65: =VLOOKUP(Tabela25[[#This Row],[GRUPO]],[1]Produto!H290:I593,2,0) -> Adicional | D65: Ad Café | E65: 8.5 | F65: 9 | G65: =VLOOKUP(Tabela25[[#This Row],[CÓDIGO]],'[1]Estrutura Loja'!$B$3:$M$2941,5,0) -> 9.511241 | H65: =E65-G65 -> -1.011241 | I65: 8.5 | J65: =(Tabela25[[#This Row],[PREÇO PRATICADO]]-((Tabela25[[#This Row],[PREÇO PRATICADO]])*([1]Informações!$H$6+[1]Informações!$H$15+[1]Informações!$H$19+[1]Informações!$H$20))-Tabela25[[#This Row],[CUSTO]])/Tabela25[[#This Row],[PREÇO PRATICADO]] -> 0.16692647 | K65: =Tabela25[[#This Row],[PREÇO PRATICADO]]*Tabela25[[#This Row],[LUCRO REAL %]] -> 1.418875 | M65: =IF(Tabela25[[#This Row],[QUANT. VENDA]]=0,0,((Tabela25[[#This Row],[CUSTO]]*Tabela25[[#This Row],[QUANT. VENDA]])/(Tabela25[[#This Row],[QUANT. VENDA]]*Tabela25[[#This Row],[PREÇO PRATICADO]]))) -> 0 | N65: =VLOOKUP(Tabela25[[#This Row],[CÓDIGO]],'[1]Estrutura Loja'!$B$3:$E$1825,4,0) -> 2.644125 | O65: =Tabela25[[#This Row],[QUANT. VENDA]]*Tabela25[[#This Row],[PREÇO PRATICADO]] -> 0 | P65: =Tabela25[[#This Row],[QUANT. VENDA]]*Tabela25[[#This Row],[CUSTO]] -> 0 | Q65: =Tabela25[[#This Row],[CUSTO]]/Tabela25[[#This Row],[PREÇO PRATICADO]] -> 0.31107353
A66: 110000034 | B66: 1100 | C66: =VLOOKUP(Tabela25[[#This Row],[GRUPO]],[1]Produto!H291:I594,2,0) -> Adicional | D66: Ad Canudinho Biju Wafer | E66: 1 | F66: 2 | G66: =VLOOKUP(Tabela25[[#This Row],[CÓDIGO]],'[1]Estrutura Loja'!$B$3:$M$2941,5,0) -> 0.40753597 | H66: =E66-G66 -> 0.59246403 | I66: 1 | J66: =(Tabela25[[#This Row],[PREÇO PRATICADO]]-((Tabela25[[#This Row],[PREÇO PRATICADO]])*([1]Informações!$H$6+[1]Informações!$H$15+[1]Informações!$H$19+[1]Informações!$H$20))-Tabela25[[#This Row],[CUSTO]])/Tabela25[[#This Row],[PREÇO PRATICADO]] -> 0.364705 | K66: =Tabela25[[#This Row],[PREÇO PRATICADO]]*Tabela25[[#This Row],[LUCRO REAL %]] -> 0.364705 | M66: =IF(Tabela25[[#This Row],[QUANT. VENDA]]=0,0,((Tabela25[[#This Row],[CUSTO]]*Tabela25[[#This Row],[QUANT. VENDA]])/(Tabela25[[#This Row],[QUANT. VENDA]]*Tabela25[[#This Row],[PREÇO PRATICADO]]))) -> 0 | N66: =VLOOKUP(Tabela25[[#This Row],[CÓDIGO]],'[1]Estrutura Loja'!$B$3:$E$1825,4,0) -> 0.113295 | O66: =Tabela25[[#This Row],[QUANT. VENDA]]*Tabela25[[#This Row],[PREÇO PRATICADO]] -> 0 | P66: =Tabela25[[#This Row],[QUANT. VENDA]]*Tabela25[[#This Row],[CUSTO]] -> 0 | Q66: =Tabela25[[#This Row],[CUSTO]]/Tabela25[[#This Row],[PREÇO PRATICADO]] -> 0.113295
A67: 110000035 | B67: 1100 | C67: =VLOOKUP(Tabela25[[#This Row],[GRUPO]],[1]Produto!H292:I596,2,0) -> Adicional | D67: Ad Cobertura Chocolate | E67: 1 | F67: 1 | G67: =VLOOKUP(Tabela25[[#This Row],[CÓDIGO]],'[1]Estrutura Loja'!$B$3:$M$2941,5,0) -> 0.64996913 | H67: =E67-G67 -> 0.35003087 | I67: 1 | J67: =(Tabela25[[#This Row],[PREÇO PRATICADO]]-((Tabela25[[#This Row],[PREÇO PRATICADO]])*([1]Informações!$H$6+[1]Informações!$H$15+[1]Informações!$H$19+[1]Informações!$H$20))-Tabela25[[#This Row],[CUSTO]])/Tabela25[[#This Row],[PREÇO PRATICADO]] -> 0.29730858 | K67: =Tabela25[[#This Row],[PREÇO PRATICADO]]*Tabela25[[#This Row],[LUCRO REAL %]] -> 0.29730858 | M67: =IF(Tabela25[[#This Row],[QUANT. VENDA]]=0,0,((Tabela25[[#This Row],[CUSTO]]*Tabela25[[#This Row],[QUANT. VENDA]])/(Tabela25[[#This Row],[QUANT. VENDA]]*Tabela25[[#This Row],[PREÇO PRATICADO]]))) -> 0 | N67: =VLOOKUP(Tabela25[[#This Row],[CÓDIGO]],'[1]Estrutura Loja'!$B$3:$E$1825,4,0) -> 0.18069142 | O67: =Tabela25[[#This Row],[QUANT. VENDA]]*Tabela25[[#This Row],[PREÇO PRATICADO]] -> 0 | P67: =Tabela25[[#This Row],[QUANT. VENDA]]*Tabela25[[#This Row],[CUSTO]] -> 0 | Q67: =Tabela25[[#This Row],[CUSTO]]/Tabela25[[#This Row],[PREÇO PRATICADO]] -> 0.18069142
A68: 110000036 | B68: 1100 | C68: =VLOOKUP(Tabela25[[#This Row],[GRUPO]],[1]Produto!H294:I598,2,0) -> Adicional | D68: Ad Cobertura Morango | E68: 1 | F68: 1 | G68: =VLOOKUP(Tabela25[[#This Row],[CÓDIGO]],'[1]Estrutura Loja'!$B$3:$M$2941,5,0) -> 0.71031294 | H68: =E68-G68 -> 0.28968706 | I68: 1 | J68: =(Tabela25[[#This Row],[PREÇO PRATICADO]]-((Tabela25[[#This Row],[PREÇO PRATICADO]])*([1]Informações!$H$6+[1]Informações!$H$15+[1]Informações!$H$19+[1]Informações!$H$20))-Tabela25[[#This Row],[CUSTO]])/Tabela25[[#This Row],[PREÇO PRATICADO]] -> 0.280533 | K68: =Tabela25[[#This Row],[PREÇO PRATICADO]]*Tabela25[[#This Row],[LUCRO REAL %]] -> 0.280533 | M68: =IF(Tabela25[[#This Row],[QUANT. VENDA]]=0,0,((Tabela25[[#This Row],[CUSTO]]*Tabela25[[#This Row],[QUANT. VENDA]])/(Tabela25[[#This Row],[QUANT. VENDA]]*Tabela25[[#This Row],[PREÇO PRATICADO]]))) -> 0 | N68: =VLOOKUP(Tabela25[[#This Row],[CÓDIGO]],'[1]Estrutura Loja'!$B$3:$E$1825,4,0) -> 0.197467 | O68: =Tabela25[[#This Row],[QUANT. VENDA]]*Tabela25[[#This Row],[PREÇO PRATICADO]] -> 0 | P68: =Tabela25[[#This Row],[QUANT. VENDA]]*Tabela25[[#This Row],[CUSTO]] -> 0 | Q68: =Tabela25[[#This Row],[CUSTO]]/Tabela25[[#This Row],[PREÇO PRATICADO]] -> 0.197467
A69: 110000037 | B69: 1100 | C69: =VLOOKUP(Tabela25[[#This Row],[GRUPO]],[1]Produto!H295:I599,2,0) -> Adicional | D69: Ad Cobertura Caramelo | E69: 1 | F69: 1 | G69: =VLOOKUP(Tabela25[[#This Row],[CÓDIGO]],'[1]Estrutura Loja'!$B$3:$M$2941,5,0) -> 0.64526201 | H69: =E69-G69 -> 0.35473799 | I69: 1 | J69: =(Tabela25[[#This Row],[PREÇO PRATICADO]]-((Tabela25[[#This Row],[PREÇO PRATICADO]])*([1]Informações!$H$6+[1]Informações!$H$15+[1]Informações!$H$19+[1]Informações!$H$20))-Tabela25[[#This Row],[CUSTO]])/Tabela25[[#This Row],[PREÇO PRATICADO]] -> 0.29861716 | K69: =Tabela25[[#This Row],[PREÇO PRATICADO]]*Tabela25[[#This Row],[LUCRO REAL %]] -> 0.29861716 | M69: =IF(Tabela25[[#This Row],[QUANT. VENDA]]=0,0,((Tabela25[[#This Row],[CUSTO]]*Tabela25[[#This Row],[QUANT. VENDA]])/(Tabela25[[#This Row],[QUANT. VENDA]]*Tabela25[[#This Row],[PREÇO PRATICADO]]))) -> 0 | N69: =VLOOKUP(Tabela25[[#This Row],[CÓDIGO]],'[1]Estrutura Loja'!$B$3:$E$1825,4,0) -> 0.17938284 | O69: =Tabela25[[#This Row],[QUANT. VENDA]]*Tabela25[[#This Row],[PREÇO PRATICADO]] -> 0 | P69: =Tabela25[[#This Row],[QUANT. VENDA]]*Tabela25[[#This Row],[CUSTO]] -> 0 | Q69: =Tabela25[[#This Row],[CUSTO]]/Tabela25[[#This Row],[PREÇO PRATICADO]] -> 0.17938284
A70: 110000038 | B70: 1100 | C70: =VLOOKUP(Tabela25[[#This Row],[GRUPO]],[1]Produto!H58:I400,2,0) -> Adicional | D70: Ad Farofa Especial | E70: 1.5 | F70: 3 | G70: =VLOOKUP(Tabela25[[#This Row],[CÓDIGO]],'[1]Estrutura Loja'!$B$3:$M$2941,5,0) -> 1.7173908 | H70: =E70-G70 -> -0.21739084 | I70: 1.5 | J70: =(Tabela25[[#This Row],[PREÇO PRATICADO]]-((Tabela25[[#This Row],[PREÇO PRATICADO]])*([1]Informações!$H$6+[1]Informações!$H$15+[1]Informações!$H$19+[1]Informações!$H$20))-Tabela25[[#This Row],[CUSTO]])/Tabela25[[#This Row],[PREÇO PRATICADO]] -> 0.15971023 | K70: =Tabela25[[#This Row],[PREÇO PRATICADO]]*Tabela25[[#This Row],[LUCRO REAL %]] -> 0.23956535 | M70: =IF(Tabela25[[#This Row],[QUANT. VENDA]]=0,0,((Tabela25[[#This Row],[CUSTO]]*Tabela25[[#This Row],[QUANT. VENDA]])/(Tabela25[[#This Row],[QUANT. VENDA]]*Tabela25[[#This Row],[PREÇO PRATICADO]]))) -> 0 | N70: =VLOOKUP(Tabela25[[#This Row],[CÓDIGO]],'[1]Estrutura Loja'!$B$3:$E$1825,4,0) -> 0.47743465 | O70: =Tabela25[[#This Row],[QUANT. VENDA]]*Tabela25[[#This Row],[PREÇO PRATICADO]] -> 0 | P70: =Tabela25[[#This Row],[QUANT. VENDA]]*Tabela25[[#This Row],[CUSTO]] -> 0 | Q70: =Tabela25[[#This Row],[CUSTO]]/Tabela25[[#This Row],[PREÇO PRATICADO]] -> 0.31828977
A71: 110000039 | B71: 1100 | C71: =VLOOKUP(Tabela25[[#This Row],[GRUPO]],[1]Produto!H59:I402,2,0) -> Adicional | D71: Ad Amendoim | E71: 1.5 | F71: 3 | G71: =VLOOKUP(Tabela25[[#This Row],[CÓDIGO]],'[1]Estrutura Loja'!$B$3:$M$2941,5,0) -> 1.2768705 | H71: =E71-G71 -> 0.2231295 | I71: 1.5 | J71: =(Tabela25[[#This Row],[PREÇO PRATICADO]]-((Tabela25[[#This Row],[PREÇO PRATICADO]])*([1]Informações!$H$6+[1]Informações!$H$15+[1]Informações!$H$19+[1]Informações!$H$20))-Tabela25[[#This Row],[CUSTO]])/Tabela25[[#This Row],[PREÇO PRATICADO]] -> 0.24135333 | K71: =Tabela25[[#This Row],[PREÇO PRATICADO]]*Tabela25[[#This Row],[LUCRO REAL %]] -> 0.36203 | M71: =IF(Tabela25[[#This Row],[QUANT. VENDA]]=0,0,((Tabela25[[#This Row],[CUSTO]]*Tabela25[[#This Row],[QUANT. VENDA]])/(Tabela25[[#This Row],[QUANT. VENDA]]*Tabela25[[#This Row],[PREÇO PRATICADO]]))) -> 0 | N71: =VLOOKUP(Tabela25[[#This Row],[CÓDIGO]],'[1]Estrutura Loja'!$B$3:$E$1825,4,0) -> 0.35497 | O71: =Tabela25[[#This Row],[QUANT. VENDA]]*Tabela25[[#This Row],[PREÇO PRATICADO]] -> 0 | P71: =Tabela25[[#This Row],[QUANT. VENDA]]*Tabela25[[#This Row],[CUSTO]] -> 0 | Q71: =Tabela25[[#This Row],[CUSTO]]/Tabela25[[#This Row],[PREÇO PRATICADO]] -> 0.23664667
A72: 110000040 | B72: 1100 | C72: =VLOOKUP(Tabela25[[#This Row],[GRUPO]],[1]Produto!H60:I403,2,0) -> Adicional | D72: Ad Marshmallow torcao Fini | E72: 2.5 | F72: 3 | G72: =VLOOKUP(Tabela25[[#This Row],[CÓDIGO]],'[1]Estrutura Loja'!$B$3:$M$2941,5,0) -> 3.1888921 | H72: =E72-G72 -> -0.68889209 | I72: 2.5 | J72: =(Tabela25[[#This Row],[PREÇO PRATICADO]]-((Tabela25[[#This Row],[PREÇO PRATICADO]])*([1]Informações!$H$6+[1]Informações!$H$15+[1]Informações!$H$19+[1]Informações!$H$20))-Tabela25[[#This Row],[CUSTO]])/Tabela25[[#This Row],[PREÇO PRATICADO]] -> 0.1233952 | K72: =Tabela25[[#This Row],[PREÇO PRATICADO]]*Tabela25[[#This Row],[LUCRO REAL %]] -> 0.308488 | M72: =IF(Tabela25[[#This Row],[QUANT. VENDA]]=0,0,((Tabela25[[#This Row],[CUSTO]]*Tabela25[[#This Row],[QUANT. VENDA]])/(Tabela25[[#This Row],[QUANT. VENDA]]*Tabela25[[#This Row],[PREÇO PRATICADO]]))) -> 0 | N72: =VLOOKUP(Tabela25[[#This Row],[CÓDIGO]],'[1]Estrutura Loja'!$B$3:$E$1825,4,0) -> 0.886512 | O72: =Tabela25[[#This Row],[QUANT. VENDA]]*Tabela25[[#This Row],[PREÇO PRATICADO]] -> 0 | P72: =Tabela25[[#This Row],[QUANT. VENDA]]*Tabela25[[#This Row],[CUSTO]] -> 0 | Q72: =Tabela25[[#This Row],[CUSTO]]/Tabela25[[#This Row],[PREÇO PRATICADO]] -> 0.3546048
A73: 110000041 | B73: 1100 | C73: =VLOOKUP(Tabela25[[#This Row],[GRUPO]],[1]Produto!H62:I405,2,0) -> Adicional | D73: Ad Mini Disqueti | E73: 5 | F73: 6 | G73: =VLOOKUP(Tabela25[[#This Row],[CÓDIGO]],'[1]Estrutura Loja'!$B$3:$M$2941,5,0) -> 5.9273381 | H73: =E73-G73 -> -0.92733813 | I73: 5 | J73: =(Tabela25[[#This Row],[PREÇO PRATICADO]]-((Tabela25[[#This Row],[PREÇO PRATICADO]])*([1]Informações!$H$6+[1]Informações!$H$15+[1]Informações!$H$19+[1]Informações!$H$20))-Tabela25[[#This Row],[CUSTO]])/Tabela25[[#This Row],[PREÇO PRATICADO]] -> 0.14844 | K73: =Tabela25[[#This Row],[PREÇO PRATICADO]]*Tabela25[[#This Row],[LUCRO REAL %]] -> 0.7422 | M73: =IF(Tabela25[[#This Row],[QUANT. VENDA]]=0,0,((Tabela25[[#This Row],[CUSTO]]*Tabela25[[#This Row],[QUANT. VENDA]])/(Tabela25[[#This Row],[QUANT. VENDA]]*Tabela25[[#This Row],[PREÇO PRATICADO]]))) -> 0 | N73: =VLOOKUP(Tabela25[[#This Row],[CÓDIGO]],'[1]Estrutura Loja'!$B$3:$E$1825,4,0) -> 1.6478 | O73: =Tabela25[[#This Row],[QUANT. VENDA]]*Tabela25[[#This Row],[PREÇO PRATICADO]] -> 0 | P73: =Tabela25[[#This Row],[QUANT. VENDA]]*Tabela25[[#This Row],[CUSTO]] -> 0 | Q73: =Tabela25[[#This Row],[CUSTO]]/Tabela25[[#This Row],[PREÇO PRATICADO]] -> 0.32956
A74: 110000042 | B74: 1100 | C74: =VLOOKUP(Tabela25[[#This Row],[GRUPO]],[1]Produto!H56:I398,2,0) -> Adicional | D74: Ad Morango | E74: 4 | F74: 5 | G74: =VLOOKUP(Tabela25[[#This Row],[CÓDIGO]],'[1]Estrutura Loja'!$B$3:$M$2941,5,0) -> 3.7769784 | H74: =E74-G74 -> 0.22302158 | I74: 4 | J74: =(Tabela25[[#This Row],[PREÇO PRATICADO]]-((Tabela25[[#This Row],[PREÇO PRATICADO]])*([1]Informações!$H$6+[1]Informações!$H$15+[1]Informações!$H$19+[1]Informações!$H$20))-Tabela25[[#This Row],[CUSTO]])/Tabela25[[#This Row],[PREÇO PRATICADO]] -> 0.2155 | K74: =Tabela25[[#This Row],[PREÇO PRATICADO]]*Tabela25[[#This Row],[LUCRO REAL %]] -> 0.862 | M74: =IF(Tabela25[[#This Row],[QUANT. VENDA]]=0,0,((Tabela25[[#This Row],[CUSTO]]*Tabela25[[#This Row],[QUANT. VENDA]])/(Tabela25[[#This Row],[QUANT. VENDA]]*Tabela25[[#This Row],[PREÇO PRATICADO]]))) -> 0 | N74: =VLOOKUP(Tabela25[[#This Row],[CÓDIGO]],'[1]Estrutura Loja'!$B$3:$E$1825,4,0) -> 1.05 | O74: =Tabela25[[#This Row],[QUANT. VENDA]]*Tabela25[[#This Row],[PREÇO PRATICADO]] -> 0 | P74: =Tabela25[[#This Row],[QUANT. VENDA]]*Tabela25[[#This Row],[CUSTO]] -> 0 | Q74: =Tabela25[[#This Row],[CUSTO]]/Tabela25[[#This Row],[PREÇO PRATICADO]] -> 0.2625
A75: 110000043 | B75: 1100 | C75: =VLOOKUP(Tabela25[[#This Row],[GRUPO]],[1]Produto!H57:I399,2,0) -> Adicional | D75: Ad pacote casquinhas 10 unid. - Delivery | E75: 10 | F75: 10 | G75: =VLOOKUP(Tabela25[[#This Row],[CÓDIGO]],'[1]Estrutura Loja'!$B$3:$M$2941,5,0) -> 11.293165 | H75: =E75-G75 -> -1.2931655 | I75: 10 | J75: =(Tabela25[[#This Row],[PREÇO PRATICADO]]-((Tabela25[[#This Row],[PREÇO PRATICADO]])*([1]Informações!$H$6+[1]Informações!$H$15+[1]Informações!$H$19+[1]Informações!$H$20))-Tabela25[[#This Row],[CUSTO]])/Tabela25[[#This Row],[PREÇO PRATICADO]] -> 0.16405 | K75: =Tabela25[[#This Row],[PREÇO PRATICADO]]*Tabela25[[#This Row],[LUCRO REAL %]] -> 1.6405 | M75: =IF(Tabela25[[#This Row],[QUANT. VENDA]]=0,0,((Tabela25[[#This Row],[CUSTO]]*Tabela25[[#This Row],[QUANT. VENDA]])/(Tabela25[[#This Row],[QUANT. VENDA]]*Tabela25[[#This Row],[PREÇO PRATICADO]]))) -> 0 | N75: =VLOOKUP(Tabela25[[#This Row],[CÓDIGO]],'[1]Estrutura Loja'!$B$3:$E$1825,4,0) -> 3.1395 | O75: =Tabela25[[#This Row],[QUANT. VENDA]]*Tabela25[[#This Row],[PREÇO PRATICADO]] -> 0 | P75: =Tabela25[[#This Row],[QUANT. VENDA]]*Tabela25[[#This Row],[CUSTO]] -> 0 | Q75: =Tabela25[[#This Row],[CUSTO]]/Tabela25[[#This Row],[PREÇO PRATICADO]] -> 0.31395
A76: 110000044 | B76: 1100 | C76: =VLOOKUP(Tabela25[[#This Row],[GRUPO]],[1]Produto!H63:I406,2,0) -> Adicional | D76: Ad pacote cascão 10 unid. - Delivery | E76: 14 | F76: 14 | G76: =VLOOKUP(Tabela25[[#This Row],[CÓDIGO]],'[1]Estrutura Loja'!$B$3:$M$2941,5,0) -> 17.27488 | H76: =E76-G76 -> -3.2748801 | I76: 14 | J76: =(Tabela25[[#This Row],[PREÇO PRATICADO]]-((Tabela25[[#This Row],[PREÇO PRATICADO]])*([1]Informações!$H$6+[1]Informações!$H$15+[1]Informações!$H$19+[1]Informações!$H$20))-Tabela25[[#This Row],[CUSTO]])/Tabela25[[#This Row],[PREÇO PRATICADO]] -> 0.13497024 | K76: =Tabela25[[#This Row],[PREÇO PRATICADO]]*Tabela25[[#This Row],[LUCRO REAL %]] -> 1.8895833 | M76: =IF(Tabela25[[#This Row],[QUANT. VENDA]]=0,0,((Tabela25[[#This Row],[CUSTO]]*Tabela25[[#This Row],[QUANT. VENDA]])/(Tabela25[[#This Row],[QUANT. VENDA]]*Tabela25[[#This Row],[PREÇO PRATICADO]]))) -> 0 | N76: =VLOOKUP(Tabela25[[#This Row],[CÓDIGO]],'[1]Estrutura Loja'!$B$3:$E$1825,4,0) -> 4.8024167 | O76: =Tabela25[[#This Row],[QUANT. VENDA]]*Tabela25[[#This Row],[PREÇO PRATICADO]] -> 0 | P76: =Tabela25[[#This Row],[QUANT. VENDA]]*Tabela25[[#This Row],[CUSTO]] -> 0 | Q76: =Tabela25[[#This Row],[CUSTO]]/Tabela25[[#This Row],[PREÇO PRATICADO]] -> 0.34302976
A77: 110000045 | B77: 1100 | C77: =VLOOKUP(Tabela25[[#This Row],[GRUPO]],[1]Produto!H63:I407,2,0) -> Adicional | D77: Ad Bolo Petit Gateau | E77: 12 | F77: 12 | G77: =VLOOKUP(Tabela25[[#This Row],[CÓDIGO]],'[1]Estrutura Loja'!$B$3:$M$2941,5,0) -> 21.940719 | H77: =E77-G77 -> -9.9407194 | I77: 22 | J77: =(Tabela25[[#This Row],[PREÇO PRATICADO]]-((Tabela25[[#This Row],[PREÇO PRATICADO]])*([1]Informações!$H$6+[1]Informações!$H$15+[1]Informações!$H$19+[1]Informações!$H$20))-Tabela25[[#This Row],[CUSTO]])/Tabela25[[#This Row],[PREÇO PRATICADO]] -> 0.20074909 | K77: =Tabela25[[#This Row],[PREÇO PRATICADO]]*Tabela25[[#This Row],[LUCRO REAL %]] -> 4.41648 | M77: =IF(Tabela25[[#This Row],[QUANT. VENDA]]=0,0,((Tabela25[[#This Row],[CUSTO]]*Tabela25[[#This Row],[QUANT. VENDA]])/(Tabela25[[#This Row],[QUANT. VENDA]]*Tabela25[[#This Row],[PREÇO PRATICADO]]))) -> 0 | N77: =VLOOKUP(Tabela25[[#This Row],[CÓDIGO]],'[1]Estrutura Loja'!$B$3:$E$1825,4,0) -> 6.09952 | O77: =Tabela25[[#This Row],[QUANT. VENDA]]*Tabela25[[#This Row],[PREÇO PRATICADO]] -> 0 | P77: =Tabela25[[#This Row],[QUANT. VENDA]]*Tabela25[[#This Row],[CUSTO]] -> 0 | Q77: =Tabela25[[#This Row],[CUSTO]]/Tabela25[[#This Row],[PREÇO PRATICADO]] -> 0.27725091
A78: 110000046 | B78: 1100 | C78: =VLOOKUP(Tabela25[[#This Row],[GRUPO]],[1]Produto!H81:I426,2,0) -> Adicional | D78: Petit Gateau Chiquinho (4x80 gr) | E78: 24 | F78: 26 | G78: =VLOOKUP(Tabela25[[#This Row],[CÓDIGO]],'[1]Estrutura Loja'!$B$3:$M$2941,5,0) -> 28.549383 | H78: =E78-G78 -> -4.5493827 | I78: 24 | J78: =(Tabela25[[#This Row],[PREÇO PRATICADO]]-((Tabela25[[#This Row],[PREÇO PRATICADO]])*([1]Informações!$H$6+[1]Informações!$H$19+[1]Informações!$H$20))-Tabela25[[#This Row],[CUSTO]])/Tabela25[[#This Row],[PREÇO PRATICADO]] -> 0.077166667 | K78: =Tabela25[[#This Row],[PREÇO PRATICADO]]*Tabela25[[#This Row],[LUCRO REAL %]] -> 1.852 | M78: =IF(Tabela25[[#This Row],[QUANT. VENDA]]=0,0,((Tabela25[[#This Row],[CUSTO]]*Tabela25[[#This Row],[QUANT. VENDA]])/(Tabela25[[#This Row],[QUANT. VENDA]]*Tabela25[[#This Row],[PREÇO PRATICADO]]))) -> 0 | N78: =VLOOKUP(Tabela25[[#This Row],[CÓDIGO]],'[1]Estrutura Loja'!$B$3:$E$1825,4,0) -> 18.5 | O78: =Tabela25[[#This Row],[QUANT. VENDA]]*Tabela25[[#This Row],[PREÇO PRATICADO]] -> 0 | P78: =Tabela25[[#This Row],[QUANT. VENDA]]*Tabela25[[#This Row],[CUSTO]] -> 0 | Q78: =Tabela25[[#This Row],[CUSTO]]/Tabela25[[#This Row],[PREÇO PRATICADO]] -> 0.77083333
A79: 110000047 | B79: 1100 | C79: =VLOOKUP(Tabela25[[#This Row],[GRUPO]],[1]Produto!H82:I427,2,0) -> Adicional | D79: Petit Gateau Chiquinho (1x80 gr) | E79: 7 | F79: 8 | G79: =VLOOKUP(Tabela25[[#This Row],[CÓDIGO]],'[1]Estrutura Loja'!$B$3:$M$2941,5,0) -> 7.7546296 | H79: =E79-G79 -> -0.75462963 | I79: 7 | J79: =(Tabela25[[#This Row],[PREÇO PRATICADO]]-((Tabela25[[#This Row],[PREÇO PRATICADO]])*([1]Informações!$H$6+[1]Informações!$H$19+[1]Informações!$H$20))-Tabela25[[#This Row],[CUSTO]])/Tabela25[[#This Row],[PREÇO PRATICADO]] -> 0.13014286 | K79: =Tabela25[[#This Row],[PREÇO PRATICADO]]*Tabela25[[#This Row],[LUCRO REAL %]] -> 0.911 | M79: =IF(Tabela25[[#This Row],[QUANT. VENDA]]=0,0,((Tabela25[[#This Row],[CUSTO]]*Tabela25[[#This Row],[QUANT. VENDA]])/(Tabela25[[#This Row],[QUANT. VENDA]]*Tabela25[[#This Row],[PREÇO PRATICADO]]))) -> 0 | N79: =VLOOKUP(Tabela25[[#This Row],[CÓDIGO]],'[1]Estrutura Loja'!$B$3:$E$1825,4,0) -> 5.025 | O79: =Tabela25[[#This Row],[QUANT. VENDA]]*Tabela25[[#This Row],[PREÇO PRATICADO]] -> 0 | P79: =Tabela25[[#This Row],[QUANT. VENDA]]*Tabela25[[#This Row],[CUSTO]] -> 0 | Q79: =Tabela25[[#This Row],[CUSTO]]/Tabela25[[#This Row],[PREÇO PRATICADO]] -> 0.71785714
A80: 110000048 | B80: 1100 | C80: =VLOOKUP(Tabela25[[#This Row],[GRUPO]],[1]Produto!H83:I428,2,0) -> Adicional | D80: Ad Biscoito Maizena | E80: 1.5 | F80: 2.5 | G80: =VLOOKUP(Tabela25[[#This Row],[CÓDIGO]],'[1]Estrutura Loja'!$B$3:$M$2941,5,0) -> 1.1305242 | H80: =E80-G80 -> 0.36947585 | I80: 1.5 | J80: =(Tabela25[[#This Row],[PREÇO PRATICADO]]-((Tabela25[[#This Row],[PREÇO PRATICADO]])*([1]Informações!$H$6+[1]Informações!$H$15+[1]Informações!$H$19+[1]Informações!$H$20))-Tabela25[[#This Row],[CUSTO]])/Tabela25[[#This Row],[PREÇO PRATICADO]] -> 0.26847619 | K80: =Tabela25[[#This Row],[PREÇO PRATICADO]]*Tabela25[[#This Row],[LUCRO REAL %]] -> 0.40271429 | M80: =IF(Tabela25[[#This Row],[QUANT. VENDA]]=0,0,((Tabela25[[#This Row],[CUSTO]]*Tabela25[[#This Row],[QUANT. VENDA]])/(Tabela25[[#This Row],[QUANT. VENDA]]*Tabela25[[#This Row],[PREÇO PRATICADO]]))) -> 0 | N80: =VLOOKUP(Tabela25[[#This Row],[CÓDIGO]],'[1]Estrutura Loja'!$B$3:$E$1825,4,0) -> 0.31428571 | O80: =Tabela25[[#This Row],[QUANT. VENDA]]*Tabela25[[#This Row],[PREÇO PRATICADO]] -> 0 | P80: =Tabela25[[#This Row],[QUANT. VENDA]]*Tabela25[[#This Row],[CUSTO]] -> 0 | Q80: =Tabela25[[#This Row],[CUSTO]]/Tabela25[[#This Row],[PREÇO PRATICADO]] -> 0.20952381
A81: 110000049 | B81: 1100 | C81: =VLOOKUP(Tabela25[[#This Row],[GRUPO]],[1]Produto!H86:I434,2,0) -> Adicional | D81: Ad Pistache | E81: 7 | F81: 8 | G81: =VLOOKUP(Tabela25[[#This Row],[CÓDIGO]],'[1]Estrutura Loja'!$B$3:$M$2941,5,0) -> 7.8084173 | H81: =E81-G81 -> -0.80841727 | I81: 7 | J81: =(Tabela25[[#This Row],[PREÇO PRATICADO]]-((Tabela25[[#This Row],[PREÇO PRATICADO]])*([1]Informações!$H$6+[1]Informações!$H$15+[1]Informações!$H$19+[1]Informações!$H$20))-Tabela25[[#This Row],[CUSTO]])/Tabela25[[#This Row],[PREÇO PRATICADO]] -> 0.16789429 | K81: =Tabela25[[#This Row],[PREÇO PRATICADO]]*Tabela25[[#This Row],[LUCRO REAL %]] -> 1.17526 | M81: =IF(Tabela25[[#This Row],[QUANT. VENDA]]=0,0,((Tabela25[[#This Row],[CUSTO]]*Tabela25[[#This Row],[QUANT. VENDA]])/(Tabela25[[#This Row],[QUANT. VENDA]]*Tabela25[[#This Row],[PREÇO PRATICADO]]))) -> 0 | N81: =VLOOKUP(Tabela25[[#This Row],[CÓDIGO]],'[1]Estrutura Loja'!$B$3:$E$1825,4,0) -> 2.17074 | O81: =Tabela25[[#This Row],[QUANT. VENDA]]*Tabela25[[#This Row],[PREÇO PRATICADO]] -> 0 | P81: =Tabela25[[#This Row],[QUANT. VENDA]]*Tabela25[[#This Row],[CUSTO]] -> 0 | Q81: =Tabela25[[#This Row],[CUSTO]]/Tabela25[[#This Row],[PREÇO PRATICADO]] -> 0.31010571
A82: 110000050 | B82: 1100 | C82: =VLOOKUP(Tabela25[[#This Row],[GRUPO]],[1]Produto!H79:I428,2,0) -> Adicional | D82: Ad Mesclado Dubai | E82: 6 | F82: 7 | G82: =VLOOKUP(Tabela25[[#This Row],[CÓDIGO]],'[1]Estrutura Loja'!$B$3:$M$2941,5,0) -> 5.6115108 | H82: =E82-G82 -> 0.38848921 | I82: 6 | J82: =(Tabela25[[#This Row],[PREÇO PRATICADO]]-((Tabela25[[#This Row],[PREÇO PRATICADO]])*([1]Informações!$H$6+[1]Informações!$H$15+[1]Informações!$H$19+[1]Informações!$H$20))-Tabela25[[#This Row],[CUSTO]])/Tabela25[[#This Row],[PREÇO PRATICADO]] -> 0.218 | K82: =Tabela25[[#This Row],[PREÇO PRATICADO]]*Tabela25[[#This Row],[LUCRO REAL %]] -> 1.308 | M82: =IF(Tabela25[[#This Row],[QUANT. VENDA]]=0,0,((Tabela25[[#This Row],[CUSTO]]*Tabela25[[#This Row],[QUANT. VENDA]])/(Tabela25[[#This Row],[QUANT. VENDA]]*Tabela25[[#This Row],[PREÇO PRATICADO]]))) -> 0 | N82: =VLOOKUP(Tabela25[[#This Row],[CÓDIGO]],'[1]Estrutura Loja'!$B$3:$E$1825,4,0) -> 1.56 | O82: =Tabela25[[#This Row],[QUANT. VENDA]]*Tabela25[[#This Row],[PREÇO PRATICADO]] -> 0 | P82: =Tabela25[[#This Row],[QUANT. VENDA]]*Tabela25[[#This Row],[CUSTO]] -> 0 | Q82: =Tabela25[[#This Row],[CUSTO]]/Tabela25[[#This Row],[PREÇO PRATICADO]] -> 0.26
A83: 130000001 | B83: 1100 | C83: =VLOOKUP(Tabela25[[#This Row],[GRUPO]],[1]Produto!H84:I433,2,0) -> Adicional | D83: Ad Puro Leite | E83: 2 | F83: 3 | G83: =VLOOKUP(Tabela25[[#This Row],[CÓDIGO]],'[1]Estrutura Loja'!$B$3:$M$2941,5,0) -> 1.5431655 | H83: =E83-G83 -> 0.45683453 | I83: 2 | J83: =(Tabela25[[#This Row],[PREÇO PRATICADO]]-((Tabela25[[#This Row],[PREÇO PRATICADO]])*([1]Informações!$H$6+[1]Informações!$H$15+[1]Informações!$H$19+[1]Informações!$H$20))-Tabela25[[#This Row],[CUSTO]])/Tabela25[[#This Row],[PREÇO PRATICADO]] -> 0.2635 | K83: =Tabela25[[#This Row],[PREÇO PRATICADO]]*Tabela25[[#This Row],[LUCRO REAL %]] -> 0.527 | M83: =IF(Tabela25[[#This Row],[QUANT. VENDA]]=0,0,((Tabela25[[#This Row],[CUSTO]]*Tabela25[[#This Row],[QUANT. VENDA]])/(Tabela25[[#This Row],[QUANT. VENDA]]*Tabela25[[#This Row],[PREÇO PRATICADO]]))) -> 0 | N83: =VLOOKUP(Tabela25[[#This Row],[CÓDIGO]],'[1]Estrutura Loja'!$B$3:$E$1825,4,0) -> 0.429 | O83: =Tabela25[[#This Row],[QUANT. VENDA]]*Tabela25[[#This Row],[PREÇO PRATICADO]] -> 0 | P83: =Tabela25[[#This Row],[QUANT. VENDA]]*Tabela25[[#This Row],[CUSTO]] -> 0 | Q83: =Tabela25[[#This Row],[CUSTO]]/Tabela25[[#This Row],[PREÇO PRATICADO]] -> 0.2145
A84: 130000002 | B84: 1100 | C84: =VLOOKUP(Tabela25[[#This Row],[GRUPO]],[1]Produto!H85:I434,2,0) -> Adicional | D84: Ad Coco Malásia | E84: 5 | F84: 7 | G84: =VLOOKUP(Tabela25[[#This Row],[CÓDIGO]],'[1]Estrutura Loja'!$B$3:$M$2941,5,0) -> 4.6739209 | H84: =E84-G84 -> 0.32607914 | I84: 5 | J84: =(Tabela25[[#This Row],[PREÇO PRATICADO]]-((Tabela25[[#This Row],[PREÇO PRATICADO]])*([1]Informações!$H$6+[1]Informações!$H$15+[1]Informações!$H$19+[1]Informações!$H$20))-Tabela25[[#This Row],[CUSTO]])/Tabela25[[#This Row],[PREÇO PRATICADO]] -> 0.21813 | K84: =Tabela25[[#This Row],[PREÇO PRATICADO]]*Tabela25[[#This Row],[LUCRO REAL %]] -> 1.09065 | M84: =IF(Tabela25[[#This Row],[QUANT. VENDA]]=0,0,((Tabela25[[#This Row],[CUSTO]]*Tabela25[[#This Row],[QUANT. VENDA]])/(Tabela25[[#This Row],[QUANT. VENDA]]*Tabela25[[#This Row],[PREÇO PRATICADO]]))) -> 0 | N84: =VLOOKUP(Tabela25[[#This Row],[CÓDIGO]],'[1]Estrutura Loja'!$B$3:$E$1825,4,0) -> 1.29935 | O84: =Tabela25[[#This Row],[QUANT. VENDA]]*Tabela25[[#This Row],[PREÇO PRATICADO]] -> 0 | P84: =Tabela25[[#This Row],[QUANT. VENDA]]*Tabela25[[#This Row],[CUSTO]] -> 0 | Q84: =Tabela25[[#This Row],[CUSTO]]/Tabela25[[#This Row],[PREÇO PRATICADO]] -> 0.25987
A85: 130000003 | B85: 1100 | C85: =VLOOKUP(Tabela25[[#This Row],[GRUPO]],[1]Produto!H85:I434,2,0) -> Adicional | D85: Ad Amarena | E85: 12 | F85: 14 | G85: =VLOOKUP(Tabela25[[#This Row],[CÓDIGO]],'[1]Estrutura Loja'!$B$3:$M$2941,5,0) -> 11.106115 | H85: =E85-G85 -> 0.89388489 | I85: 12 | J85: =(Tabela25[[#This Row],[PREÇO PRATICADO]]-((Tabela25[[#This Row],[PREÇO PRATICADO]])*([1]Informações!$H$6+[1]Informações!$H$15+[1]Informações!$H$19+[1]Informações!$H$20))-Tabela25[[#This Row],[CUSTO]])/Tabela25[[#This Row],[PREÇO PRATICADO]] -> 0.22070833 | K85: =Tabela25[[#This Row],[PREÇO PRATICADO]]*Tabela25[[#This Row],[LUCRO REAL %]] -> 2.6485 | M85: =IF(Tabela25[[#This Row],[QUANT. VENDA]]=0,0,((Tabela25[[#This Row],[CUSTO]]*Tabela25[[#This Row],[QUANT. VENDA]])/(Tabela25[[#This Row],[QUANT. VENDA]]*Tabela25[[#This Row],[PREÇO PRATICADO]]))) -> 0 | N85: =VLOOKUP(Tabela25[[#This Row],[CÓDIGO]],'[1]Estrutura Loja'!$B$3:$E$1825,4,0) -> 3.0875 | O85: =Tabela25[[#This Row],[QUANT. VENDA]]*Tabela25[[#This Row],[PREÇO PRATICADO]] -> 0 | P85: =Tabela25[[#This Row],[QUANT. VENDA]]*Tabela25[[#This Row],[CUSTO]] -> 0 | Q85: =Tabela25[[#This Row],[CUSTO]]/Tabela25[[#This Row],[PREÇO PRATICADO]] -> 0.25729167
A86: 130000004 | B86: 1100 | C86: =VLOOKUP(Tabela25[[#This Row],[GRUPO]],[1]Produto!H86:I435,2,0) -> Adicional | D86: Ad Calda Fondue | E86: 4.5 | F86: 5 | G86: =VLOOKUP(Tabela25[[#This Row],[CÓDIGO]],'[1]Estrutura Loja'!$B$3:$M$2941,5,0) -> 4.1652107 | H86: =E86-G86 -> 0.33478931 | I86: 4.5 | J86: =(Tabela25[[#This Row],[PREÇO PRATICADO]]-((Tabela25[[#This Row],[PREÇO PRATICADO]])*([1]Informações!$H$6+[1]Informações!$H$15+[1]Informações!$H$19+[1]Informações!$H$20))-Tabela25[[#This Row],[CUSTO]])/Tabela25[[#This Row],[PREÇO PRATICADO]] -> 0.22068254 | K86: =Tabela25[[#This Row],[PREÇO PRATICADO]]*Tabela25[[#This Row],[LUCRO REAL %]] -> 0.99307143 | M86: =IF(Tabela25[[#This Row],[QUANT. VENDA]]=0,0,((Tabela25[[#This Row],[CUSTO]]*Tabela25[[#This Row],[QUANT. VENDA]])/(Tabela25[[#This Row],[QUANT. VENDA]]*Tabela25[[#This Row],[PREÇO PRATICADO]]))) -> 0 | N86: =VLOOKUP(Tabela25[[#This Row],[CÓDIGO]],'[1]Estrutura Loja'!$B$3:$E$1825,4,0) -> 1.1579286 | O86: =Tabela25[[#This Row],[QUANT. VENDA]]*Tabela25[[#This Row],[PREÇO PRATICADO]] -> 0 | P86: =Tabela25[[#This Row],[QUANT. VENDA]]*Tabela25[[#This Row],[CUSTO]] -> 0 | Q86: =Tabela25[[#This Row],[CUSTO]]/Tabela25[[#This Row],[PREÇO PRATICADO]] -> 0.25731746
A87: 130000006 | B87: 1100 | C87: =VLOOKUP(Tabela25[[#This Row],[GRUPO]],[1]Produto!H87:I436,2,0) -> Adicional | D87: Ad. Creme de Ninho | E87: 2 | F87: 4 | G87: =VLOOKUP(Tabela25[[#This Row],[CÓDIGO]],'[1]Estrutura Loja'!$B$3:$M$2941,5,0) -> 1.9543052 | H87: =E87-G87 -> 0.045694787 | I87: 2 | J87: =(Tabela25[[#This Row],[PREÇO PRATICADO]]-((Tabela25[[#This Row],[PREÇO PRATICADO]])*([1]Informações!$H$6+[1]Informações!$H$15+[1]Informações!$H$19+[1]Informações!$H$20))-Tabela25[[#This Row],[CUSTO]])/Tabela25[[#This Row],[PREÇO PRATICADO]] -> 0.20635158 | K87: =Tabela25[[#This Row],[PREÇO PRATICADO]]*Tabela25[[#This Row],[LUCRO REAL %]] -> 0.41270315 | M87: =IF(Tabela25[[#This Row],[QUANT. VENDA]]=0,0,((Tabela25[[#This Row],[CUSTO]]*Tabela25[[#This Row],[QUANT. VENDA]])/(Tabela25[[#This Row],[QUANT. VENDA]]*Tabela25[[#This Row],[PREÇO PRATICADO]]))) -> 0 | N87: =VLOOKUP(Tabela25[[#This Row],[CÓDIGO]],'[1]Estrutura Loja'!$B$3:$E$1825,4,0) -> 0.54329685 | O87: =Tabela25[[#This Row],[QUANT. VENDA]]*Tabela25[[#This Row],[PREÇO PRATICADO]] -> 0 | P87: =Tabela25[[#This Row],[QUANT. VENDA]]*Tabela25[[#This Row],[CUSTO]] -> 0 | Q87: =Tabela25[[#This Row],[CUSTO]]/Tabela25[[#This Row],[PREÇO PRATICADO]] -> 0.27164842
A88: 190000001 | B88: 1100 | C88: =VLOOKUP(Tabela25[[#This Row],[GRUPO]],[1]Produto!H87:I435,2,0) -> Adicional | D88: Kit viagem único | E88: 2 | F88: 3 | G88: =VLOOKUP(Tabela25[[#This Row],[CÓDIGO]],'[1]Estrutura Loja'!$B$3:$M$2941,5,0) -> 2.1864877 | H88: =E88-G88 -> -0.18648765 | I88: 2 | J88: =(Tabela25[[#This Row],[PREÇO PRATICADO]]-((Tabela25[[#This Row],[PREÇO PRATICADO]])*([1]Informações!$H$6+[1]Informações!$H$19+[1]Informações!$H$20))-Tabela25[[#This Row],[CUSTO]])/Tabela25[[#This Row],[PREÇO PRATICADO]] -> 0.139578 | K88: =Tabela25[[#This Row],[PREÇO PRATICADO]]*Tabela25[[#This Row],[LUCRO REAL %]] -> 0.279156 | M88: =IF(Tabela25[[#This Row],[QUANT. VENDA]]=0,0,((Tabela25[[#This Row],[CUSTO]]*Tabela25[[#This Row],[QUANT. VENDA]])/(Tabela25[[#This Row],[QUANT. VENDA]]*Tabela25[[#This Row],[PREÇO PRATICADO]]))) -> 0 | N88: =VLOOKUP(Tabela25[[#This Row],[CÓDIGO]],'[1]Estrutura Loja'!$B$3:$E$1825,4,0) -> 1.416844 | O88: =Tabela25[[#This Row],[QUANT. VENDA]]*Tabela25[[#This Row],[PREÇO PRATICADO]] -> 0 | P88: =Tabela25[[#This Row],[QUANT. VENDA]]*Tabela25[[#This Row],[CUSTO]] -> 0 | Q88: =Tabela25[[#This Row],[CUSTO]]/Tabela25[[#This Row],[PREÇO PRATICADO]] -> 0.708422
A89: 190000002 | B89: 1100 | C89: =VLOOKUP(Tabela25[[#This Row],[GRUPO]],[1]Produto!H99:I442,2,0) -> Adicional | D89: Kit viagem duplo | E89: 2 | F89: 3 | G89: =VLOOKUP(Tabela25[[#This Row],[CÓDIGO]],'[1]Estrutura Loja'!$B$3:$M$2941,5,0) -> 1.6140463 | H89: =E89-G89 -> 0.3859537 | I89: 2 | J89: =(Tabela25[[#This Row],[PREÇO PRATICADO]]-((Tabela25[[#This Row],[PREÇO PRATICADO]])*([1]Informações!$H$6+[1]Informações!$H$19+[1]Informações!$H$20))-Tabela25[[#This Row],[CUSTO]])/Tabela25[[#This Row],[PREÇO PRATICADO]] -> 0.325049 | K89: =Tabela25[[#This Row],[PREÇO PRATICADO]]*Tabela25[[#This Row],[LUCRO REAL %]] -> 0.650098 | M89: =IF(Tabela25[[#This Row],[QUANT. VENDA]]=0,0,((Tabela25[[#This Row],[CUSTO]]*Tabela25[[#This Row],[QUANT. VENDA]])/(Tabela25[[#This Row],[QUANT. VENDA]]*Tabela25[[#This Row],[PREÇO PRATICADO]]))) -> 0 | N89: =VLOOKUP(Tabela25[[#This Row],[CÓDIGO]],'[1]Estrutura Loja'!$B$3:$E$1825,4,0) -> 1.045902 | O89: =Tabela25[[#This Row],[QUANT. VENDA]]*Tabela25[[#This Row],[PREÇO PRATICADO]] -> 0 | P89: =Tabela25[[#This Row],[QUANT. VENDA]]*Tabela25[[#This Row],[CUSTO]] -> 0 | Q89: =Tabela25[[#This Row],[CUSTO]]/Tabela25[[#This Row],[PREÇO PRATICADO]] -> 0.522951
A90: 101300001 | B90: 1013 | C90: =VLOOKUP(Tabela25[[#This Row],[GRUPO]],[1]Produto!H139:I511,2,0) -> Big Sundae | D90: Big Sundae Cobertura Caramelo | E90: 11 | F90: 13 | G90: =VLOOKUP(Tabela25[[#This Row],[CÓDIGO]],'[1]Estrutura Loja'!$B$3:$M$2941,5,0) -> 10.883418 | H90: =E90-G90 -> 0.11658241 | I90: 11 | J90: =(Tabela25[[#This Row],[PREÇO PRATICADO]]-((Tabela25[[#This Row],[PREÇO PRATICADO]])*([1]Informações!$H$6+[1]Informações!$H$15+[1]Informações!$H$19+[1]Informações!$H$20))-Tabela25[[#This Row],[CUSTO]])/Tabela25[[#This Row],[PREÇO PRATICADO]] -> 0.20294636 | K90: =Tabela25[[#This Row],[PREÇO PRATICADO]]*Tabela25[[#This Row],[LUCRO REAL %]] -> 2.2324099 | M90: =IF(Tabela25[[#This Row],[QUANT. VENDA]]=0,0,((Tabela25[[#This Row],[CUSTO]]*Tabela25[[#This Row],[QUANT. VENDA]])/(Tabela25[[#This Row],[QUANT. VENDA]]*Tabela25[[#This Row],[PREÇO PRATICADO]]))) -> 0 | N90: =VLOOKUP(Tabela25[[#This Row],[CÓDIGO]],'[1]Estrutura Loja'!$B$3:$E$1825,4,0) -> 3.0255901 | O90: =Tabela25[[#This Row],[QUANT. VENDA]]*Tabela25[[#This Row],[PREÇO PRATICADO]] -> 0 | P90: =Tabela25[[#This Row],[QUANT. VENDA]]*Tabela25[[#This Row],[CUSTO]] -> 0 | Q90: =Tabela25[[#This Row],[CUSTO]]/Tabela25[[#This Row],[PREÇO PRATICADO]] -> 0.27505364
A91: 101300002 | B91: 1013 | C91: =VLOOKUP(Tabela25[[#This Row],[GRUPO]],[1]Produto!H140:I512,2,0) -> Big Sundae | D91: Big Sundae Cobertura Chocolate | E91: 11 | F91: 13 | G91: =VLOOKUP(Tabela25[[#This Row],[CÓDIGO]],'[1]Estrutura Loja'!$B$3:$M$2941,5,0) -> 10.890478 | H91: =E91-G91 -> 0.10952172 | I91: 11 | J91: =(Tabela25[[#This Row],[PREÇO PRATICADO]]-((Tabela25[[#This Row],[PREÇO PRATICADO]])*([1]Informações!$H$6+[1]Informações!$H$15+[1]Informações!$H$19+[1]Informações!$H$20))-Tabela25[[#This Row],[CUSTO]])/Tabela25[[#This Row],[PREÇO PRATICADO]] -> 0.20276791 | K91: =Tabela25[[#This Row],[PREÇO PRATICADO]]*Tabela25[[#This Row],[LUCRO REAL %]] -> 2.230447 | M91: =IF(Tabela25[[#This Row],[QUANT. VENDA]]=0,0,((Tabela25[[#This Row],[CUSTO]]*Tabela25[[#This Row],[QUANT. VENDA]])/(Tabela25[[#This Row],[QUANT. VENDA]]*Tabela25[[#This Row],[PREÇO PRATICADO]]))) -> 0 | N91: =VLOOKUP(Tabela25[[#This Row],[CÓDIGO]],'[1]Estrutura Loja'!$B$3:$E$1825,4,0) -> 3.027553 | O91: =Tabela25[[#This Row],[QUANT. VENDA]]*Tabela25[[#This Row],[PREÇO PRATICADO]] -> 0 | P91: =Tabela25[[#This Row],[QUANT. VENDA]]*Tabela25[[#This Row],[CUSTO]] -> 0 | Q91: =Tabela25[[#This Row],[CUSTO]]/Tabela25[[#This Row],[PREÇO PRATICADO]] -> 0.27523209
A92: 101300003 | B92: 1013 | C92: =VLOOKUP(Tabela25[[#This Row],[GRUPO]],[1]Produto!H152:I513,2,0) -> Big Sundae | D92: Big Sundae Cobertura Morango | E92: 11 | F92: 13 | G92: =VLOOKUP(Tabela25[[#This Row],[CÓDIGO]],'[1]Estrutura Loja'!$B$3:$M$2941,5,0) -> 10.980994 | H92: =E92-G92 -> 0.019006014 | I92: 11 | J92: =(Tabela25[[#This Row],[PREÇO PRATICADO]]-((Tabela25[[#This Row],[PREÇO PRATICADO]])*([1]Informações!$H$6+[1]Informações!$H$15+[1]Informações!$H$19+[1]Informações!$H$20))-Tabela25[[#This Row],[CUSTO]])/Tabela25[[#This Row],[PREÇO PRATICADO]] -> 0.20048033 | K92: =Tabela25[[#This Row],[PREÇO PRATICADO]]*Tabela25[[#This Row],[LUCRO REAL %]] -> 2.2052837 | M92: =IF(Tabela25[[#This Row],[QUANT. VENDA]]=0,0,((Tabela25[[#This Row],[CUSTO]]*Tabela25[[#This Row],[QUANT. VENDA]])/(Tabela25[[#This Row],[QUANT. VENDA]]*Tabela25[[#This Row],[PREÇO PRATICADO]]))) -> 0 | N92: =VLOOKUP(Tabela25[[#This Row],[CÓDIGO]],'[1]Estrutura Loja'!$B$3:$E$1825,4,0) -> 3.0527163 | O92: =Tabela25[[#This Row],[QUANT. VENDA]]*Tabela25[[#This Row],[PREÇO PRATICADO]] -> 0 | P92: =Tabela25[[#This Row],[QUANT. VENDA]]*Tabela25[[#This Row],[CUSTO]] -> 0 | Q92: =Tabela25[[#This Row],[CUSTO]]/Tabela25[[#This Row],[PREÇO PRATICADO]] -> 0.27751967
A93: 101300004 | B93: 1013 | C93: =VLOOKUP(Tabela25[[#This Row],[GRUPO]],[1]Produto!H153:I514,2,0) -> Big Sundae | D93: Big Sundae Chocotino Turbo | E93: 20 | F93: 22 | G93: =VLOOKUP(Tabela25[[#This Row],[CÓDIGO]],'[1]Estrutura Loja'!$B$3:$M$2941,5,0) -> 20.4349 | H93: =E93-G93 -> -0.43489975 | I93: 20 | J93: =(Tabela25[[#This Row],[PREÇO PRATICADO]]-((Tabela25[[#This Row],[PREÇO PRATICADO]])*([1]Informações!$H$6+[1]Informações!$H$15+[1]Informações!$H$19+[1]Informações!$H$20))-Tabela25[[#This Row],[CUSTO]])/Tabela25[[#This Row],[PREÇO PRATICADO]] -> 0.19395489 | K93: =Tabela25[[#This Row],[PREÇO PRATICADO]]*Tabela25[[#This Row],[LUCRO REAL %]] -> 3.8790979 | M93: =IF(Tabela25[[#This Row],[QUANT. VENDA]]=0,0,((Tabela25[[#This Row],[CUSTO]]*Tabela25[[#This Row],[QUANT. VENDA]])/(Tabela25[[#This Row],[QUANT. VENDA]]*Tabela25[[#This Row],[PREÇO PRATICADO]]))) -> 0 | N93: =VLOOKUP(Tabela25[[#This Row],[CÓDIGO]],'[1]Estrutura Loja'!$B$3:$E$1825,4,0) -> 5.6809021 | O93: =Tabela25[[#This Row],[QUANT. VENDA]]*Tabela25[[#This Row],[PREÇO PRATICADO]] -> 0 | P93: =Tabela25[[#This Row],[QUANT. VENDA]]*Tabela25[[#This Row],[CUSTO]] -> 0 | Q93: =Tabela25[[#This Row],[CUSTO]]/Tabela25[[#This Row],[PREÇO PRATICADO]] -> 0.28404511
A94: 102200001 | B94: 1022 | C94: =VLOOKUP(Tabela25[[#This Row],[GRUPO]],[1]Produto!H119:I442,2,0) -> Bubble Waffle | D94: Bubble Waffle no Cone c/ Chantilly | E94: 14 | F94: 16 | G94: =VLOOKUP(Tabela25[[#This Row],[CÓDIGO]],'[1]Estrutura Loja'!$B$3:$M$2941,5,0) -> 13.82544 | H94: =E94-G94 -> 0.17456 | I94: 15 | J94: =(Tabela25[[#This Row],[PREÇO PRATICADO]]-((Tabela25[[#This Row],[PREÇO PRATICADO]])*([1]Informações!$H$6+[1]Informações!$H$15+[1]Informações!$H$19+[1]Informações!$H$20))-Tabela25[[#This Row],[CUSTO]])/Tabela25[[#This Row],[PREÇO PRATICADO]] -> 0.22176851 | K94: =Tabela25[[#This Row],[PREÇO PRATICADO]]*Tabela25[[#This Row],[LUCRO REAL %]] -> 3.3265277 | M94: =IF(Tabela25[[#This Row],[QUANT. VENDA]]=0,0,((Tabela25[[#This Row],[CUSTO]]*Tabela25[[#This Row],[QUANT. VENDA]])/(Tabela25[[#This Row],[QUANT. VENDA]]*Tabela25[[#This Row],[PREÇO PRATICADO]]))) -> 0 | N94: =VLOOKUP(Tabela25[[#This Row],[CÓDIGO]],'[1]Estrutura Loja'!$B$3:$E$1825,4,0) -> 3.8434723 | O94: =Tabela25[[#This Row],[QUANT. VENDA]]*Tabela25[[#This Row],[PREÇO PRATICADO]] -> 0 | P94: =Tabela25[[#This Row],[QUANT. VENDA]]*Tabela25[[#This Row],[CUSTO]] -> 0 | Q94: =Tabela25[[#This Row],[CUSTO]]/Tabela25[[#This Row],[PREÇO PRATICADO]] -> 0.25623149
A95: 102200002 | B95: 1022 | C95: =VLOOKUP(Tabela25[[#This Row],[GRUPO]],[1]Produto!H120:I443,2,0) -> Bubble Waffle | D95: Bubble Waffle no Cone c/Sorvetes | E95: 14 | F95: 16 | G95: =VLOOKUP(Tabela25[[#This Row],[CÓDIGO]],'[1]Estrutura Loja'!$B$3:$M$2941,5,0) -> 14.384024 | H95: =E95-G95 -> -0.38402355 | I95: 15 | J95: =(Tabela25[[#This Row],[PREÇO PRATICADO]]-((Tabela25[[#This Row],[PREÇO PRATICADO]])*([1]Informações!$H$6+[1]Informações!$H$15+[1]Informações!$H$19+[1]Informações!$H$20))-Tabela25[[#This Row],[CUSTO]])/Tabela25[[#This Row],[PREÇO PRATICADO]] -> 0.2114161 | K95: =Tabela25[[#This Row],[PREÇO PRATICADO]]*Tabela25[[#This Row],[LUCRO REAL %]] -> 3.1712415 | M95: =IF(Tabela25[[#This Row],[QUANT. VENDA]]=0,0,((Tabela25[[#This Row],[CUSTO]]*Tabela25[[#This Row],[QUANT. VENDA]])/(Tabela25[[#This Row],[QUANT. VENDA]]*Tabela25[[#This Row],[PREÇO PRATICADO]]))) -> 0 | N95: =VLOOKUP(Tabela25[[#This Row],[CÓDIGO]],'[1]Estrutura Loja'!$B$3:$E$1825,4,0) -> 3.9987585 | O95: =Tabela25[[#This Row],[QUANT. VENDA]]*Tabela25[[#This Row],[PREÇO PRATICADO]] -> 0 | P95: =Tabela25[[#This Row],[QUANT. VENDA]]*Tabela25[[#This Row],[CUSTO]] -> 0 | Q95: =Tabela25[[#This Row],[CUSTO]]/Tabela25[[#This Row],[PREÇO PRATICADO]] -> 0.2665839
A96: 102200098 | B96: 1022 | C96: =VLOOKUP(Tabela25[[#This Row],[GRUPO]],[1]Produto!H91:I440,2,0) -> Bubble Waffle | D96: Bubble Waffle no Cone c/ Chantilly G | E96: 19 | F96: 21 | G96: =VLOOKUP(Tabela25[[#This Row],[CÓDIGO]],'[1]Estrutura Loja'!$B$3:$M$2941,5,0) -> 19.368308 | H96: =E96-G96 -> -0.36830806 | I96: 20 | J96: =(Tabela25[[#This Row],[PREÇO PRATICADO]]-((Tabela25[[#This Row],[PREÇO PRATICADO]])*([1]Informações!$H$6+[1]Informações!$H$15+[1]Informações!$H$19+[1]Informações!$H$20))-Tabela25[[#This Row],[CUSTO]])/Tabela25[[#This Row],[PREÇO PRATICADO]] -> 0.20878052 | K96: =Tabela25[[#This Row],[PREÇO PRATICADO]]*Tabela25[[#This Row],[LUCRO REAL %]] -> 4.1756104 | M96: =IF(Tabela25[[#This Row],[QUANT. VENDA]]=0,0,((Tabela25[[#This Row],[CUSTO]]*Tabela25[[#This Row],[QUANT. VENDA]])/(Tabela25[[#This Row],[QUANT. VENDA]]*Tabela25[[#This Row],[PREÇO PRATICADO]]))) -> 0 | N96: =VLOOKUP(Tabela25[[#This Row],[CÓDIGO]],'[1]Estrutura Loja'!$B$3:$E$1825,4,0) -> 5.3843896 | O96: =Tabela25[[#This Row],[QUANT. VENDA]]*Tabela25[[#This Row],[PREÇO PRATICADO]] -> 0 | P96: =Tabela25[[#This Row],[QUANT. VENDA]]*Tabela25[[#This Row],[CUSTO]] -> 0 | Q96: =Tabela25[[#This Row],[CUSTO]]/Tabela25[[#This Row],[PREÇO PRATICADO]] -> 0.26921948
A97: 102200099 | B97: 1022 | C97: =VLOOKUP(Tabela25[[#This Row],[GRUPO]],[1]Produto!H92:I441,2,0) -> Bubble Waffle | D97: Bubble Waffle no Cone c/Sorvetes G | E97: 21 | F97: 23 | G97: =VLOOKUP(Tabela25[[#This Row],[CÓDIGO]],'[1]Estrutura Loja'!$B$3:$M$2941,5,0) -> 21.785475 | H97: =E97-G97 -> -0.78547547 | I97: 21 | J97: =(Tabela25[[#This Row],[PREÇO PRATICADO]]-((Tabela25[[#This Row],[PREÇO PRATICADO]])*([1]Informações!$H$6+[1]Informações!$H$15+[1]Informações!$H$19+[1]Informações!$H$20))-Tabela25[[#This Row],[CUSTO]])/Tabela25[[#This Row],[PREÇO PRATICADO]] -> 0.1896018 | K97: =Tabela25[[#This Row],[PREÇO PRATICADO]]*Tabela25[[#This Row],[LUCRO REAL %]] -> 3.9816378 | M97: =IF(Tabela25[[#This Row],[QUANT. VENDA]]=0,0,((Tabela25[[#This Row],[CUSTO]]*Tabela25[[#This Row],[QUANT. VENDA]])/(Tabela25[[#This Row],[QUANT. VENDA]]*Tabela25[[#This Row],[PREÇO PRATICADO]]))) -> 0 | N97: =VLOOKUP(Tabela25[[#This Row],[CÓDIGO]],'[1]Estrutura Loja'!$B$3:$E$1825,4,0) -> 6.0563622 | O97: =Tabela25[[#This Row],[QUANT. VENDA]]*Tabela25[[#This Row],[PREÇO PRATICADO]] -> 0 | P97: =Tabela25[[#This Row],[QUANT. VENDA]]*Tabela25[[#This Row],[CUSTO]] -> 0 | Q97: =Tabela25[[#This Row],[CUSTO]]/Tabela25[[#This Row],[PREÇO PRATICADO]] -> 0.2883982
A98: 120000001 | B98: 1022 | C98: =VLOOKUP(Tabela25[[#This Row],[GRUPO]],[1]Produto!H121:I444,2,0) -> Bubble Waffle | D98: B.W Amendoim Granulado | E98: 1.5 | F98: 2.5 | G98: =VLOOKUP(Tabela25[[#This Row],[CÓDIGO]],'[1]Estrutura Loja'!$B$3:$M$2941,5,0) -> 1.2768705 | H98: =E98-G98 -> 0.2231295 | I98: 1.5 | J98: =(Tabela25[[#This Row],[PREÇO PRATICADO]]-((Tabela25[[#This Row],[PREÇO PRATICADO]])*([1]Informações!$H$6+[1]Informações!$H$15+[1]Informações!$H$19+[1]Informações!$H$20))-Tabela25[[#This Row],[CUSTO]])/Tabela25[[#This Row],[PREÇO PRATICADO]] -> 0.24135333 | K98: =Tabela25[[#This Row],[PREÇO PRATICADO]]*Tabela25[[#This Row],[LUCRO REAL %]] -> 0.36203 | M98: =IF(Tabela25[[#This Row],[QUANT. VENDA]]=0,0,((Tabela25[[#This Row],[CUSTO]]*Tabela25[[#This Row],[QUANT. VENDA]])/(Tabela25[[#This Row],[QUANT. VENDA]]*Tabela25[[#This Row],[PREÇO PRATICADO]]))) -> 0 | N98: =VLOOKUP(Tabela25[[#This Row],[CÓDIGO]],'[1]Estrutura Loja'!$B$3:$E$1825,4,0) -> 0.35497 | O98: =Tabela25[[#This Row],[QUANT. VENDA]]*Tabela25[[#This Row],[PREÇO PRATICADO]] -> 0 | P98: =Tabela25[[#This Row],[QUANT. VENDA]]*Tabela25[[#This Row],[CUSTO]] -> 0 | Q98: =Tabela25[[#This Row],[CUSTO]]/Tabela25[[#This Row],[PREÇO PRATICADO]] -> 0.23664667
A99: 120000002 | B99: 1022 | C99: =VLOOKUP(Tabela25[[#This Row],[GRUPO]],[1]Produto!H122:I445,2,0) -> Bubble Waffle | D99: B.W Banana | E99: 1 | F99: 2 | G99: =VLOOKUP(Tabela25[[#This Row],[CÓDIGO]],'[1]Estrutura Loja'!$B$3:$M$2941,5,0) -> 0.45928058 | H99: =E99-G99 -> 0.54071942 | I99: 1 | J99: =(Tabela25[[#This Row],[PREÇO PRATICADO]]-((Tabela25[[#This Row],[PREÇO PRATICADO]])*([1]Informações!$H$6+[1]Informações!$H$15+[1]Informações!$H$19+[1]Informações!$H$20))-Tabela25[[#This Row],[CUSTO]])/Tabela25[[#This Row],[PREÇO PRATICADO]] -> 0.35032 | K99: =Tabela25[[#This Row],[PREÇO PRATICADO]]*Tabela25[[#This Row],[LUCRO REAL %]] -> 0.35032 | M99: =IF(Tabela25[[#This Row],[QUANT. VENDA]]=0,0,((Tabela25[[#This Row],[CUSTO]]*Tabela25[[#This Row],[QUANT. VENDA]])/(Tabela25[[#This Row],[QUANT. VENDA]]*Tabela25[[#This Row],[PREÇO PRATICADO]]))) -> 0 | N99: =VLOOKUP(Tabela25[[#This Row],[CÓDIGO]],'[1]Estrutura Loja'!$B$3:$E$1825,4,0) -> 0.12768 | O99: =Tabela25[[#This Row],[QUANT. VENDA]]*Tabela25[[#This Row],[PREÇO PRATICADO]] -> 0 | P99: =Tabela25[[#This Row],[QUANT. VENDA]]*Tabela25[[#This Row],[CUSTO]] -> 0 | Q99: =Tabela25[[#This Row],[CUSTO]]/Tabela25[[#This Row],[PREÇO PRATICADO]] -> 0.12768
A100: 120000003 | B100: 1022 | C100: =VLOOKUP(Tabela25[[#This Row],[GRUPO]],[1]Produto!H123:I446,2,0) -> Bubble Waffle | D100: B.W Morango | E100: 6.5 | F100: 7.5 | G100: =VLOOKUP(Tabela25[[#This Row],[CÓDIGO]],'[1]Estrutura Loja'!$B$3:$M$2941,5,0) -> 5.6654676 | H100: =E100-G100 -> 0.83453237 | I100: 6.5 | J100: =(Tabela25[[#This Row],[PREÇO PRATICADO]]-((Tabela25[[#This Row],[PREÇO PRATICADO]])*([1]Informações!$H$6+[1]Informações!$H$15+[1]Informações!$H$19+[1]Informações!$H$20))-Tabela25[[#This Row],[CUSTO]])/Tabela25[[#This Row],[PREÇO PRATICADO]] -> 0.23569231 | K100: =Tabela25[[#This Row],[PREÇO PRATICADO]]*Tabela25[[#This Row],[LUCRO REAL %]] -> 1.532 | M100: =IF(Tabela25[[#This Row],[QUANT. VENDA]]=0,0,((Tabela25[[#This Row],[CUSTO]]*Tabela25[[#This Row],[QUANT. VENDA]])/(Tabela25[[#This Row],[QUANT. VENDA]]*Tabela25[[#This Row],[PREÇO PRATICADO]]))) -> 0 | N100: =VLOOKUP(Tabela25[[#This Row],[CÓDIGO]],'[1]Estrutura Loja'!$B$3:$E$1825,4,0) -> 1.575 | O100: =Tabela25[[#This Row],[QUANT. VENDA]]*Tabela25[[#This Row],[PREÇO PRATICADO]] -> 0 | P100: =Tabela25[[#This Row],[QUANT. VENDA]]*Tabela25[[#This Row],[CUSTO]] -> 0 | Q100: =Tabela25[[#This Row],[CUSTO]]/Tabela25[[#This Row],[PREÇO PRATICADO]] -> 0.24230769
A101: 120000004 | B101: 1022 | C101: =VLOOKUP(Tabela25[[#This Row],[GRUPO]],[1]Produto!H124:I460,2,0) -> Bubble Waffle | D101: B.W Mini Disqueti | E101: 6 | F101: 7 | G101: =VLOOKUP(Tabela25[[#This Row],[CÓDIGO]],'[1]Estrutura Loja'!$B$3:$M$2941,5,0) -> 5.9273381 | H101: =E101-G101 -> 0.072661871 | I101: 6 | J101: =(Tabela25[[#This Row],[PREÇO PRATICADO]]-((Tabela25[[#This Row],[PREÇO PRATICADO]])*([1]Informações!$H$6+[1]Informações!$H$15+[1]Informações!$H$19+[1]Informações!$H$20))-Tabela25[[#This Row],[CUSTO]])/Tabela25[[#This Row],[PREÇO PRATICADO]] -> 0.20336667 | K101: =Tabela25[[#This Row],[PREÇO PRATICADO]]*Tabela25[[#This Row],[LUCRO REAL %]] -> 1.2202 | M101: =IF(Tabela25[[#This Row],[QUANT. VENDA]]=0,0,((Tabela25[[#This Row],[CUSTO]]*Tabela25[[#This Row],[QUANT. VENDA]])/(Tabela25[[#This Row],[QUANT. VENDA]]*Tabela25[[#This Row],[PREÇO PRATICADO]]))) -> 0 | N101: =VLOOKUP(Tabela25[[#This Row],[CÓDIGO]],'[1]Estrutura Loja'!$B$3:$E$1825,4,0) -> 1.6478 | O101: =Tabela25[[#This Row],[QUANT. VENDA]]*Tabela25[[#This Row],[PREÇO PRATICADO]] -> 0 | P101: =Tabela25[[#This Row],[QUANT. VENDA]]*Tabela25[[#This Row],[CUSTO]] -> 0 | Q101: =Tabela25[[#This Row],[CUSTO]]/Tabela25[[#This Row],[PREÇO PRATICADO]] -> 0.27463333
A102: 120000005 | B102: 1022 | C102: =VLOOKUP(Tabela25[[#This Row],[GRUPO]],[1]Produto!H125:I461,2,0) -> Bubble Waffle | D102: B.W Granulado | E102: 2 | F102: 3 | G102: =VLOOKUP(Tabela25[[#This Row],[CÓDIGO]],'[1]Estrutura Loja'!$B$3:$M$2941,5,0) -> 1.2223093 | H102: =E102-G102 -> 0.77769072 | I102: 2 | J102: =(Tabela25[[#This Row],[PREÇO PRATICADO]]-((Tabela25[[#This Row],[PREÇO PRATICADO]])*([1]Informações!$H$6+[1]Informações!$H$15+[1]Informações!$H$19+[1]Informações!$H$20))-Tabela25[[#This Row],[CUSTO]])/Tabela25[[#This Row],[PREÇO PRATICADO]] -> 0.30809901 | K102: =Tabela25[[#This Row],[PREÇO PRATICADO]]*Tabela25[[#This Row],[LUCRO REAL %]] -> 0.61619802 | M102: =IF(Tabela25[[#This Row],[QUANT. VENDA]]=0,0,((Tabela25[[#This Row],[CUSTO]]*Tabela25[[#This Row],[QUANT. VENDA]])/(Tabela25[[#This Row],[QUANT. VENDA]]*Tabela25[[#This Row],[PREÇO PRATICADO]]))) -> 0 | N102: =VLOOKUP(Tabela25[[#This Row],[CÓDIGO]],'[1]Estrutura Loja'!$B$3:$E$1825,4,0) -> 0.33980198 | O102: =Tabela25[[#This Row],[QUANT. VENDA]]*Tabela25[[#This Row],[PREÇO PRATICADO]] -> 0 | P102: =Tabela25[[#This Row],[QUANT. VENDA]]*Tabela25[[#This Row],[CUSTO]] -> 0 | Q102: =Tabela25[[#This Row],[CUSTO]]/Tabela25[[#This Row],[PREÇO PRATICADO]] -> 0.16990099
A103: 120000006 | B103: 1022 | C103: =VLOOKUP(Tabela25[[#This Row],[GRUPO]],[1]Produto!H126:I462,2,0) -> Bubble Waffle | D103: B.W Ovomaltine | E103: 3 | F103: 3 | G103: =VLOOKUP(Tabela25[[#This Row],[CÓDIGO]],'[1]Estrutura Loja'!$B$3:$M$2941,5,0) -> 1.672211 | H103: =E103-G103 -> 1.327789 | I103: 2 | J103: =(Tabela25[[#This Row],[PREÇO PRATICADO]]-((Tabela25[[#This Row],[PREÇO PRATICADO]])*([1]Informações!$H$6+[1]Informações!$H$15+[1]Informações!$H$19+[1]Informações!$H$20))-Tabela25[[#This Row],[CUSTO]])/Tabela25[[#This Row],[PREÇO PRATICADO]] -> 0.24556267 | K103: =Tabela25[[#This Row],[PREÇO PRATICADO]]*Tabela25[[#This Row],[LUCRO REAL %]] -> 0.49112533 | M103: =IF(Tabela25[[#This Row],[QUANT. VENDA]]=0,0,((Tabela25[[#This Row],[CUSTO]]*Tabela25[[#This Row],[QUANT. VENDA]])/(Tabela25[[#This Row],[QUANT. VENDA]]*Tabela25[[#This Row],[PREÇO PRATICADO]]))) -> 0 | N103: =VLOOKUP(Tabela25[[#This Row],[CÓDIGO]],'[1]Estrutura Loja'!$B$3:$E$1825,4,0) -> 0.46487467 | O103: =Tabela25[[#This Row],[QUANT. VENDA]]*Tabela25[[#This Row],[PREÇO PRATICADO]] -> 0 | P103: =Tabela25[[#This Row],[QUANT. VENDA]]*Tabela25[[#This Row],[CUSTO]] -> 0 | Q103: =Tabela25[[#This Row],[CUSTO]]/Tabela25[[#This Row],[PREÇO PRATICADO]] -> 0.23243733
A104: 120000007 | B104: 1022 | C104: =VLOOKUP(Tabela25[[#This Row],[GRUPO]],[1]Produto!H127:I463,2,0) -> Bubble Waffle | D104: B.W Leite Condesado Moça | E104: 3 | F104: 4 | G104: =VLOOKUP(Tabela25[[#This Row],[CÓDIGO]],'[1]Estrutura Loja'!$B$3:$M$2941,5,0) -> 2.5268646 | H104: =E104-G104 -> 0.47313542 | I104: 3 | J104: =(Tabela25[[#This Row],[PREÇO PRATICADO]]-((Tabela25[[#This Row],[PREÇO PRATICADO]])*([1]Informações!$H$6+[1]Informações!$H$15+[1]Informações!$H$19+[1]Informações!$H$20))-Tabela25[[#This Row],[CUSTO]])/Tabela25[[#This Row],[PREÇO PRATICADO]] -> 0.24384388 | K104: =Tabela25[[#This Row],[PREÇO PRATICADO]]*Tabela25[[#This Row],[LUCRO REAL %]] -> 0.73153165 | M104: =IF(Tabela25[[#This Row],[QUANT. VENDA]]=0,0,((Tabela25[[#This Row],[CUSTO]]*Tabela25[[#This Row],[QUANT. VENDA]])/(Tabela25[[#This Row],[QUANT. VENDA]]*Tabela25[[#This Row],[PREÇO PRATICADO]]))) -> 0 | N104: =VLOOKUP(Tabela25[[#This Row],[CÓDIGO]],'[1]Estrutura Loja'!$B$3:$E$1825,4,0) -> 0.70246835 | O104: =Tabela25[[#This Row],[QUANT. VENDA]]*Tabela25[[#This Row],[PREÇO PRATICADO]] -> 0 | P104: =Tabela25[[#This Row],[QUANT. VENDA]]*Tabela25[[#This Row],[CUSTO]] -> 0 | Q104: =Tabela25[[#This Row],[CUSTO]]/Tabela25[[#This Row],[PREÇO PRATICADO]] -> 0.23415612
A105: 120000008 | B105: 1022 | C105: =VLOOKUP(Tabela25[[#This Row],[GRUPO]],[1]Produto!H128:I464,2,0) -> Bubble Waffle | D105: B.W Ganache Chiquinho | E105: 5 | F105: 6 | G105: =VLOOKUP(Tabela25[[#This Row],[CÓDIGO]],'[1]Estrutura Loja'!$B$3:$M$2941,5,0) -> 4.4751799 | H105: =E105-G105 -> 0.52482014 | I105: 5 | J105: =(Tabela25[[#This Row],[PREÇO PRATICADO]]-((Tabela25[[#This Row],[PREÇO PRATICADO]])*([1]Informações!$H$6+[1]Informações!$H$15+[1]Informações!$H$19+[1]Informações!$H$20))-Tabela25[[#This Row],[CUSTO]])/Tabela25[[#This Row],[PREÇO PRATICADO]] -> 0.22918 | K105: =Tabela25[[#This Row],[PREÇO PRATICADO]]*Tabela25[[#This Row],[LUCRO REAL %]] -> 1.1459 | M105: =IF(Tabela25[[#This Row],[QUANT. VENDA]]=0,0,((Tabela25[[#This Row],[CUSTO]]*Tabela25[[#This Row],[QUANT. VENDA]])/(Tabela25[[#This Row],[QUANT. VENDA]]*Tabela25[[#This Row],[PREÇO PRATICADO]]))) -> 0 | N105: =VLOOKUP(Tabela25[[#This Row],[CÓDIGO]],'[1]Estrutura Loja'!$B$3:$E$1825,4,0) -> 1.2441 | O105: =Tabela25[[#This Row],[QUANT. VENDA]]*Tabela25[[#This Row],[PREÇO PRATICADO]] -> 0 | P105: =Tabela25[[#This Row],[QUANT. VENDA]]*Tabela25[[#This Row],[CUSTO]] -> 0 | Q105: =Tabela25[[#This Row],[CUSTO]]/Tabela25[[#This Row],[PREÇO PRATICADO]] -> 0.24882
...
